roger/REWRITE/LAB3/rb1_Clock_Divider.v
`timescale 1ns/1ps

module Clock_Divider (clk, rst_n, sel, clk1_2, clk1_4, clk1_8, clk1_3, dclk);
    input clk, rst_n;
    input [2-1:0] sel;
    output clk1_2;
    output clk1_4;
    output clk1_8;
    output clk1_3;
    output dclk;

    reg dclk;       // ! miss

    clk_div2 CD2(clk, rst_n, clk1_2);
    clk_div4 CD4(clk, rst_n, clk1_4);
    clk_div8 CD8(clk, rst_n, clk1_8);
    clk_div3 CD3(clk, rst_n, clk1_3);

    always @(*) begin
        case (sel)
            2'd0:       dclk = clk1_3;
            2'd1:       dclk = clk1_2;
            2'd2:       dclk = clk1_4;
            default:    dclk = clk1_8;
        endcase
    end             // ! typo
endmodule

module clk_div2 (clk, rst_n, out);
    input clk, rst_n;
    output reg out;             // ! typo
    reg cnt;

    always @(posedge clk) begin             // ! synchronous
        if (!rst_n || cnt == 0)     cnt <= 1'b1;
        else                        cnt <= cnt - 1'b1;
    end
    always @(posedge clk) begin
        if (!rst_n || cnt == 0)     out <= 1'b1;
        else                        out <= 1'b0;
    end
endmodule

module clk_div4 (clk, rst_n, out);
    input clk, rst_n;
    output reg out;
    reg [2-1:0] cnt;

    always @(posedge clk) begin
        if (!rst_n || cnt == 0)     cnt <= 2'd3;
        else                        cnt <= cnt - 1'b1;
    end
    always @(posedge clk) begin
        if (!rst_n || cnt == 0)     out <= 1'b1;
        else                        out <= 1'b0;
    end
endmodule

module clk_div8 (clk, rst_n, out);
    input clk, rst_n;
    output reg out;
    reg [3-1:0] cnt;

    always @(posedge clk) begin
        if (!rst_n || cnt == 0)     cnt <= 3'd7;
        else                        cnt <= cnt - 1'b1;
    end
    always @(posedge clk) begin
        if (!rst_n || cnt == 0)     out <= 1'b1;
        else                        out <= 1'b0;
    end
endmodule

module clk_div3 (clk, rst_n, out);
    input clk, rst_n;
    output reg out;
    reg [2-1:0] cnt;

    always @(posedge clk) begin
        if (!rst_n || cnt == 0)     cnt <= 2'd2;
        else                        cnt <= cnt - 1'b1;
    end
    always @(posedge clk) begin
        if (!rst_n || cnt == 0)     out <= 1'b1;
        else                        out <= 1'b0;
    end
endmodule

roger/REWRITE/LAB3/rb1_Clock_Divider_t.v
`include "rb1_Clock_Divider.v"
`timescale 1ns/1ps

module Clock_Divider_t;
reg clk = 1'b1;
reg rst_n = 1'b1;
reg [1:0] sel = 2'd0;
wire clk1_2;
wire clk1_4;
wire clk1_8;
wire clk1_3;
wire dclk;

// specify duration of a clock cycle.
parameter cyc = 10;

// generate clock.
always#(cyc/2)clk = !clk;

Clock_Divider cd (
	.clk (clk),
	.rst_n (rst_n),
  	.sel (sel),
  	.clk1_2 (clk1_2),
  	.clk1_4 (clk1_4),
  	.clk1_8 (clk1_8),
  	.clk1_3 (clk1_3),
  	.dclk (dclk)
);

// uncommment and add "+access+r" to your nverilog command to dump fsdb waveform on NTHUCAD
// initial begin
//     $fsdbDumpfile("Clock_Divider.fsdb");
//     $fsdbDumpvars;
// end

initial begin
	@ (negedge clk)
	rst_n = 1'b0;
	@ (negedge clk)
	rst_n = 1'b1;
	@ (negedge clk)
	repeat (2 ** 2) begin
	#(cyc * 5) sel = sel + 1'b1;
	end
	#1 $finish;
end

initial begin
	$dumpfile("rb1.vcd");
	$dumpvars(0, Clock_Divider_t);
end

endmodule

roger/REWRITE/LAB3/rb1.vcd
$date
	Thu Oct 17 09:37:53 2024
$end
$version
	Icarus Verilog
$end
$timescale
	1ps
$end
$scope module Clock_Divider_t $end
$var wire 1 ! dclk $end
$var wire 1 " clk1_8 $end
$var wire 1 # clk1_4 $end
$var wire 1 $ clk1_3 $end
$var wire 1 % clk1_2 $end
$var parameter 32 & cyc $end
$var reg 1 ' clk $end
$var reg 1 ( rst_n $end
$var reg 2 ) sel [1:0] $end
$scope module cd $end
$var wire 1 ' clk $end
$var wire 1 ( rst_n $end
$var wire 2 * sel [1:0] $end
$var wire 1 " clk1_8 $end
$var wire 1 # clk1_4 $end
$var wire 1 $ clk1_3 $end
$var wire 1 % clk1_2 $end
$var reg 1 ! dclk $end
$scope module CD2 $end
$var wire 1 ' clk $end
$var wire 1 ( rst_n $end
$var reg 1 + cnt $end
$var reg 1 % out $end
$upscope $end
$scope module CD3 $end
$var wire 1 ' clk $end
$var wire 1 ( rst_n $end
$var reg 2 , cnt [1:0] $end
$var reg 1 $ out $end
$upscope $end
$scope module CD4 $end
$var wire 1 ' clk $end
$var wire 1 ( rst_n $end
$var reg 2 - cnt [1:0] $end
$var reg 1 # out $end
$upscope $end
$scope module CD8 $end
$var wire 1 ' clk $end
$var wire 1 ( rst_n $end
$var reg 3 . cnt [2:0] $end
$var reg 1 " out $end
$upscope $end
$upscope $end
$upscope $end
$enddefinitions $end
$comment Show the parameter values. $end
$dumpall
b1010 &
$end
#0
$dumpvars
bx .
bx -
bx ,
x+
b0 *
b0 )
1(
1'
0%
0$
0#
0"
0!
$end
#5000
0(
0'
#10000
1!
1$
b10 ,
1"
b111 .
1#
b11 -
1%
1+
1'
#15000
1(
0'
#20000
0!
0+
0%
b10 -
0#
b110 .
0"
b1 ,
0$
1'
#25000
0'
#30000
b0 ,
b101 .
b1 -
1%
1+
1'
#35000
0'
#40000
1!
0+
0%
b0 -
b100 .
b10 ,
1$
1'
#45000
0'
#50000
0!
0$
b1 ,
b11 .
1#
b11 -
1%
1+
1'
#55000
0'
#60000
0+
0%
b10 -
0#
b10 .
b0 ,
1'
#65000
0'
#70000
1!
1$
b10 ,
b1 .
b1 -
1%
1+
1'
#75000
0'
b1 )
b1 *
#80000
0!
0+
0%
b0 -
b0 .
b1 ,
0$
1'
#85000
0'
#90000
1!
b0 ,
1"
b111 .
1#
b11 -
1%
1+
1'
#95000
0'
#100000
0!
0+
0%
b10 -
0#
b110 .
0"
b10 ,
1$
1'
#105000
0'
#110000
1!
0$
b1 ,
b101 .
b1 -
1%
1+
1'
#115000
0'
#120000
0!
0+
0%
b0 -
b100 .
b0 ,
1'
#125000
0'
b10 )
b10 *
#130000
1!
1$
b10 ,
b11 .
1#
b11 -
1%
1+
1'
#135000
0'
#140000
0!
0+
0%
b10 -
0#
b10 .
b1 ,
0$
1'
#145000
0'
#150000
b0 ,
b1 .
b1 -
1%
1+
1'
#155000
0'
#160000
0+
0%
b0 -
b0 .
b10 ,
1$
1'
#165000
0'
#170000
1!
0$
b1 ,
1"
b111 .
1#
b11 -
1%
1+
1'
#175000
0'
b11 )
b11 *
#180000
0!
0+
0%
b10 -
0#
b110 .
0"
b0 ,
1'
#185000
0'
#190000
1$
b10 ,
b101 .
b1 -
1%
1+
1'
#195000
0'
#200000
0+
0%
b0 -
b100 .
b1 ,
0$
1'
#205000
0'
#210000
b0 ,
b11 .
1#
b11 -
1%
1+
1'
#215000
0'
#220000
0+
0%
b10 -
0#
b10 .
b10 ,
1$
1'
#225000
1!
0'
b0 )
b0 *
