roger/Lab5/a2_Traffic_Light_Controller.v
`timescale 1ns/1ps

module Traffic_Light_Controller (clk, rst_n, lr_has_car, hw_light, lr_light);
    input clk, rst_n;
    input lr_has_car;
    output reg [3-1:0] hw_light;
    output reg [3-1:0] lr_light;

    parameter time_yellow = 7'd24;
    parameter time_green = 7'd69;
    reg [7-1:0] cnt;

    parameter S1 = 3'd1;
    parameter S2 = 3'd2;
    parameter S3 = 3'd3;
    parameter S4 = 3'd4;
    parameter S5 = 3'd5;
    parameter S6 = 3'd6;
    reg [3-1:0] state;
    reg [3-1:0] next_state;

    always @(posedge clk) begin
        if (!rst_n) state <= S1;
        else        state <= next_state;
    end

    always @(posedge clk) begin
        if (!rst_n || state!=next_state) cnt <= 7'd0;   // state changing;
        else begin
            case (state)
                S1, S4: if (cnt != time_green)  cnt <= cnt + 1'b1;
                S2, S5: if (cnt != time_yellow) cnt <= cnt + 1'b1;
                default: cnt <= 7'd0;
            endcase
        end
    end

    always @(*) begin
        case (state)
            S1: begin
                hw_light = 3'b100;
                lr_light = 3'b001;
                next_state = (cnt == time_green && lr_has_car) ? S2 : S1;
            end
            S2: begin
                hw_light = 3'b010;
                lr_light = 3'b001;
                next_state = (cnt == time_yellow) ? S3 : S2;
            end
            S3: begin
                hw_light = 3'b001;
                lr_light = 3'b001;
                next_state = S4;
            end
            S4: begin
                hw_light = 3'b001;
                lr_light = 3'b100;
                next_state = (cnt == time_green) ? S5 : S4;
            end
            S5: begin
                hw_light = 3'b001;
                lr_light = 3'b010;
                next_state = (cnt == time_yellow) ? S6 : S5;
            end
            S6: begin
                hw_light = 3'b001;
                lr_light = 3'b001;
                next_state = S1;
            end
        endcase
    end
endmodule

roger/Lab5/a2_Traffic_Light_Controller_t.v
`include "a2_Traffic_Light_Controller.v"
`timescale 1ns/1ps

module Traffic_Light_Controller_t ();
    reg clk = 1'b0;
    reg rst_n = 1'b0;
    reg lr_has_car = 1'b0;
    wire [3-1:0] hw_light;
    wire [3-1:0] lr_light;

    Traffic_Light_Controller #(.time_green(2), .time_yellow(1)) TLC(clk, rst_n, lr_has_car, hw_light, lr_light);

    always #5 clk = ~clk;

    initial begin
        #10 rst_n = 1'b1;
        #10 lr_has_car = 1'b1;
        #150 rst_n = 1'b0; lr_has_car = 1'b0;
        #10 rst_n = 1'b1;
        #50 lr_has_car = 1'b1;
        #150 $finish;
    end

    initial begin
        $dumpfile("a2.vcd");
        $dumpvars(0, Traffic_Light_Controller_t);
    end
endmodule

roger/Lab5/a2.vcd
$date
	Sat Nov  2 23:26:18 2024
$end
$version
	Icarus Verilog
$end
$timescale
	1ps
$end
$scope module Traffic_Light_Controller_t $end
$var wire 3 ! lr_light [2:0] $end
$var wire 3 " hw_light [2:0] $end
$var reg 1 # clk $end
$var reg 1 $ lr_has_car $end
$var reg 1 % rst_n $end
$scope module TLC $end
$var wire 1 # clk $end
$var wire 1 $ lr_has_car $end
$var wire 1 % rst_n $end
$var parameter 3 & S1 $end
$var parameter 3 ' S2 $end
$var parameter 3 ( S3 $end
$var parameter 3 ) S4 $end
$var parameter 3 * S5 $end
$var parameter 3 + S6 $end
$var parameter 32 , time_green $end
$var parameter 32 - time_yellow $end
$var reg 7 . cnt [6:0] $end
$var reg 3 / hw_light [2:0] $end
$var reg 3 0 lr_light [2:0] $end
$var reg 3 1 next_state [2:0] $end
$var reg 3 2 state [2:0] $end
$upscope $end
$upscope $end
$enddefinitions $end
$comment Show the parameter values. $end
$dumpall
b1 -
b10 ,
b110 +
b101 *
b100 )
b11 (
b10 '
b1 &
$end
#0
$dumpvars
bx 2
bx 1
bx 0
bx /
bx .
0%
0$
0#
bx "
bx !
$end
#5000
b1 1
b1 !
b1 0
b100 "
b100 /
b1 2
b0 .
1#
#10000
0#
1%
#15000
b1 .
1#
#20000
0#
1$
#25000
b10 1
b10 .
1#
#30000
0#
#35000
b10 "
b10 /
b0 .
b10 2
1#
#40000
0#
#45000
b11 1
b1 .
1#
#50000
0#
#55000
b100 1
b1 "
b1 /
b0 .
b11 2
1#
#60000
0#
#65000
b100 !
b100 0
b100 2
1#
#70000
0#
#75000
b1 .
1#
#80000
0#
#85000
b101 1
b10 .
1#
#90000
0#
#95000
b10 !
b10 0
b0 .
b101 2
1#
#100000
0#
#105000
b110 1
b1 .
1#
#110000
0#
#115000
b1 1
b1 !
b1 0
b0 .
b110 2
1#
#120000
0#
#125000
b100 "
b100 /
b1 2
1#
#130000
0#
#135000
b1 .
1#
#140000
0#
#145000
b10 1
b10 .
1#
#150000
0#
#155000
b10 "
b10 /
b0 .
b10 2
1#
#160000
0#
#165000
b11 1
b1 .
1#
#170000
0#
0$
0%
#175000
b1 1
b100 "
b100 /
b0 .
b1 2
1#
#180000
0#
1%
#185000
b1 .
1#
#190000
0#
#195000
b10 .
1#
#200000
0#
#205000
1#
#210000
0#
#215000
1#
#220000
0#
#225000
1#
#230000
b10 1
0#
1$
#235000
b10 "
b10 /
b0 .
b10 2
1#
#240000
0#
#245000
b11 1
b1 .
1#
#250000
0#
#255000
b100 1
b1 "
b1 /
b0 .
b11 2
1#
#260000
0#
#265000
b100 !
b100 0
b100 2
1#
#270000
0#
#275000
b1 .
1#
#280000
0#
#285000
b101 1
b10 .
1#
#290000
0#
#295000
b10 !
b10 0
b0 .
b101 2
1#
#300000
0#
#305000
b110 1
b1 .
1#
#310000
0#
#315000
b1 1
b1 !
b1 0
b0 .
b110 2
1#
#320000
0#
#325000
b100 "
b100 /
b1 2
1#
#330000
0#
#335000
b1 .
1#
#340000
0#
#345000
b10 1
b10 .
1#
#350000
0#
#355000
b10 "
b10 /
b0 .
b10 2
1#
#360000
0#
#365000
b11 1
b1 .
1#
#370000
0#
#375000
b100 1
b1 "
b1 /
b0 .
b11 2
1#
