roger/Lab5/a3_Greatest_Common_Divisor.v
`timescale 1ns/1ps

module Greatest_Common_Divisor (clk, rst_n, start, a, b, done, gcd);
    input clk, rst_n;
    input start;
    input [16-1:0] a;
    input [16-1:0] b;
    output reg done;
    output reg [16-1:0] gcd;

    parameter WAIT = 2'b00;
    parameter CAL = 2'b01;
    parameter FINISH = 2'b10;
    reg [2-1:0] state;
    reg [2-1:0] next_state;
    reg [16-1:0] c;
    reg [16-1:0] d;
    reg delay;

    always @(posedge clk) begin
        if (!rst_n) state <= WAIT;
        else        state <= next_state;
    end

    always @(*) begin
        case (state)
            WAIT: begin
                next_state = (start == 1'b1) ? CAL : WAIT;
                gcd = 16'd0;
                done = 1'b0;
            end
            CAL: begin    
                next_state = (c==16'd0 || d==16'd0) ? FINISH : CAL;
                gcd = 16'd0;
                done = 1'b0;
            end
            FINISH: begin
                next_state = (delay) ? WAIT : FINISH;
                gcd = (c==16'd0) ? d : c;
                done = 1'b1;
            end
            default: begin   // just in case
                next_state = WAIT; 
                gcd = 16'd0;
                done = 1'b0;
            end
        endcase
    end

    always @(posedge clk) begin
        case (state)
            WAIT:   delay <= 1'b0;
            CAL:    delay <= 1'b0;
            FINISH: delay <= 1'b1;
            default:delay <= 1'b0;
        endcase
    end

    always @(posedge clk) begin
        case (state)
            WAIT: begin
                if (next_state == CAL) begin
                    c <= a;
                    d <= b;
                end else begin
                    c <= 16'd0;
                    d <= 16'd0;
                end
            end
            CAL: begin
                if (!(c==16'd0 || d==16'd0)) begin
                    if (c > d) begin
                        c <= c - d;
                        d <= d;
                    end else begin
                        c <= c;
                        d <= d - c;
                    end
                end else begin
                    c <= c;
                    d <= d;
                end
            end
            default: begin      // just in case
                c <= c;
                d <= d;
            end
        endcase
    end
endmodule

roger/Lab5/a3_Greatest_Common_Divisor_t.v
`include "a3_Greatest_Common_Divisor.v"
`timescale 1ns/1ps

module Greatest_Common_Divisor_t ();
    reg clk = 1'b0;;
    reg rst_n = 1'b0;
    reg start = 1'b0;
    reg [16-1:0] a = 16'd0;
    reg [16-1:0] b = 16'd0;
    wire done;
    wire [16-1:0] gcd;

    Greatest_Common_Divisor GCD(clk, rst_n, start, a, b, done, gcd);

    always #5 clk = ~clk;

    initial begin
        #10 rst_n = 1'b1;
        a = 16'd26;
        b = 16'd38;
        start = 1'b1;
        #40
        a = 16'd72;
        b = 16'd98;
        #180 start = 1'b0;
        a = 16'd195;
        b = 16'd240;
        #20 start = 1'b1;
        #100 start = 1'b0;
        a = 16'd216;
        b = 16'd180;
        #60 start = 1'b1;
        #30 start = 1'b0;
        #100 start = 1'b1;
        a = 16'd14;
        b = 16'd1;
        #60 start = 1'b0;
        #140
        a = 16'd28;
        b = 16'd28;
        #10 start = 1'b1;
        #60
        $finish;
    end

    initial begin
        $dumpfile("a3.vcd");
        $dumpvars(0, Greatest_Common_Divisor_t);
    end
endmodule

roger/Lab5/a3.vcd
$date
	Thu Nov  7 21:30:30 2024
$end
$version
	Icarus Verilog
$end
$timescale
	1ps
$end
$scope module Greatest_Common_Divisor_t $end
$var wire 16 ! gcd [15:0] $end
$var wire 1 " done $end
$var reg 16 # a [15:0] $end
$var reg 16 $ b [15:0] $end
$var reg 1 % clk $end
$var reg 1 & rst_n $end
$var reg 1 ' start $end
$scope module GCD $end
$var wire 16 ( a [15:0] $end
$var wire 16 ) b [15:0] $end
$var wire 1 % clk $end
$var wire 1 & rst_n $end
$var wire 1 ' start $end
$var parameter 2 * CAL $end
$var parameter 2 + FINISH $end
$var parameter 2 , WAIT $end
$var reg 16 - c [15:0] $end
$var reg 16 . d [15:0] $end
$var reg 1 / delay $end
$var reg 1 " done $end
$var reg 16 0 gcd [15:0] $end
$var reg 2 1 next_state [1:0] $end
$var reg 2 2 state [1:0] $end
$upscope $end
$upscope $end
$enddefinitions $end
$comment Show the parameter values. $end
$dumpall
b0 ,
b10 +
b1 *
$end
#0
$dumpvars
bx 2
b0 1
b0 0
x/
bx .
bx -
b0 )
b0 (
0'
0&
0%
b0 $
b0 #
0"
b0 !
$end
#5000
b0 2
0/
1%
#10000
b1 1
0%
1'
b100110 $
b100110 )
b11010 #
b11010 (
1&
#15000
b100110 .
b11010 -
b1 2
1%
#20000
0%
#25000
b1100 .
1%
#30000
0%
#35000
b1110 -
1%
#40000
0%
#45000
b10 -
1%
#50000
0%
b1100010 $
b1100010 )
b1001000 #
b1001000 (
#55000
b1010 .
1%
#60000
0%
#65000
b1000 .
1%
#70000
0%
#75000
b110 .
1%
#80000
0%
#85000
b100 .
1%
#90000
0%
#95000
b10 .
1%
#100000
0%
#105000
b10 1
b0 .
1%
#110000
0%
#115000
1"
b10 !
b10 0
b10 2
1%
#120000
0%
#125000
b0 1
1/
1%
#130000
0%
#135000
0"
b0 !
b0 0
b1 1
b0 2
1%
#140000
0%
#145000
b1 2
0/
b1100010 .
b1001000 -
1%
#150000
0%
#155000
b11010 .
1%
#160000
0%
#165000
b101110 -
1%
#170000
0%
#175000
b10100 -
1%
#180000
0%
#185000
b110 .
1%
#190000
0%
#195000
b1110 -
1%
#200000
0%
#205000
b1000 -
1%
#210000
0%
#215000
b10 -
1%
#220000
0%
#225000
b100 .
1%
#230000
0%
b11110000 $
b11110000 )
b11000011 #
b11000011 (
0'
#235000
b10 .
1%
#240000
0%
#245000
b10 1
b0 .
1%
#250000
0%
1'
#255000
1"
b10 !
b10 0
b10 2
1%
#260000
0%
#265000
b0 1
1/
1%
#270000
0%
#275000
0"
b0 !
b0 0
b1 1
b0 2
1%
#280000
0%
#285000
b1 2
0/
b11110000 .
b11000011 -
1%
#290000
0%
#295000
b101101 .
1%
#300000
0%
#305000
b10010110 -
1%
#310000
0%
#315000
b1101001 -
1%
#320000
0%
#325000
b111100 -
1%
#330000
0%
#335000
b1111 -
1%
#340000
0%
#345000
b11110 .
1%
#350000
0%
b10110100 $
b10110100 )
b11011000 #
b11011000 (
0'
#355000
b1111 .
1%
#360000
0%
#365000
b10 1
b0 .
1%
#370000
0%
#375000
1"
b1111 !
b1111 0
b10 2
1%
#380000
0%
#385000
b0 1
1/
1%
#390000
0%
#395000
0"
b0 !
b0 0
b0 2
1%
#400000
0%
#405000
0/
b0 -
1%
#410000
b1 1
0%
1'
#415000
b10110100 .
b11011000 -
b1 2
1%
#420000
0%
#425000
b100100 -
1%
#430000
0%
#435000
b10010000 .
1%
#440000
0%
0'
#445000
b1101100 .
1%
#450000
0%
#455000
b1001000 .
1%
#460000
0%
#465000
b100100 .
1%
#470000
0%
#475000
b10 1
b0 .
1%
#480000
0%
#485000
1"
b100100 !
b100100 0
b10 2
1%
#490000
0%
#495000
b0 1
1/
1%
#500000
0%
#505000
0"
b0 !
b0 0
b0 2
1%
#510000
0%
#515000
b0 -
0/
1%
#520000
0%
#525000
1%
#530000
0%
#535000
1%
#540000
b1 1
0%
b1 $
b1 )
b1110 #
b1110 (
1'
#545000
b1 2
b1 .
b1110 -
1%
#550000
0%
#555000
b1101 -
1%
#560000
0%
#565000
b1100 -
1%
#570000
0%
#575000
b1011 -
1%
#580000
0%
#585000
b1010 -
1%
#590000
0%
#595000
b1001 -
1%
#600000
0%
0'
#605000
b1000 -
1%
#610000
0%
#615000
b111 -
1%
#620000
0%
#625000
b110 -
1%
#630000
0%
#635000
b101 -
1%
#640000
0%
#645000
b100 -
1%
#650000
0%
#655000
b11 -
1%
#660000
0%
#665000
b10 -
1%
#670000
0%
#675000
b1 -
1%
#680000
0%
#685000
b10 1
b0 .
1%
#690000
0%
#695000
1"
b1 !
b1 0
b10 2
1%
#700000
0%
#705000
b0 1
1/
1%
#710000
0%
#715000
0"
b0 !
b0 0
b0 2
1%
#720000
0%
#725000
0/
b0 -
1%
#730000
0%
#735000
1%
#740000
0%
b11100 $
b11100 )
b11100 #
b11100 (
#745000
1%
#750000
b1 1
0%
1'
#755000
b11100 .
b11100 -
b1 2
1%
#760000
0%
#765000
b10 1
b0 .
1%
#770000
0%
#775000
1"
b11100 !
b11100 0
b10 2
1%
#780000
0%
#785000
b0 1
1/
1%
#790000
0%
#795000
0"
b0 !
b0 0
b1 1
b0 2
1%
#800000
0%
#805000
b1 2
0/
b11100 .
1%
