johnny/Lab3/Lab3_Team1_Parameterized_Ping_Pong_Counter.v
`timescale 1ns/1ps

module Parameterized_Ping_Pong_Counter (clk, rst_n, enable, flip, max, min, direction, out);
    input clk, rst_n;
    input enable;
    input flip;
    input [4-1:0] max;
    input [4-1:0] min;
    output reg direction;
    output reg [4-1:0] out;

    always @(posedge clk) begin
        if(!rst_n) begin //case 0
            out <= min;
            direction <= 1'b1;
        end
        else if(enable == 1) begin //case 1
            if(out < max && out > min) begin //case 1-1
                if(direction == 1) begin
                    if(flip == 1) begin
                        direction <= !direction;
                        out <= out-1;
                    end
                    else out <= out+1;
                end
                else begin 
                    if(flip == 1) begin
                        direction <= !direction;
                        out <= out+1;
                    end
                    else out <= out-1;
                end
            end
            else if(out > max || out < min) out <= out; //case 1-2
            else if(out == min && out != max) begin //case 1-3
                out <= out+1;
                if(direction == 0) direction <= !direction;
            end
            else if(out == max && out != min) begin //case 1-4
                out <= out-1;
                if(direction == 1) direction <= !direction;
            end
            else out <= out;
        end
        else out <= out;
    end
endmodule

johnny/Lab3/Lab3_Team1_Parameterized_Ping_Pong_Counter_t.v
`include "Lab3_Team1_Parameterized_Ping_Pong_Counter.v"
`timescale 1ns/1ps

module Parameterized_Ping_Pong_Counter_t();
    reg clk = 0, rst_n = 0, enable = 1, flip = 0;
    reg [3:0] max = 4'd4, min = 4'd0;
    wire direction;
    wire [3:0] out;
    Parameterized_Ping_Pong_Counter PPPC(clk, rst_n, enable, flip, max, min, direction, out);

    always #5 clk = !clk;
    
    initial begin
        #150 flip = 1;
        #10 flip = 0;
    end

    initial begin
        #260 flip = 1;
        #10 flip = 0;
    end

    initial begin
        #280 flip = 1;
        #10 flip = 0;
    end

    initial begin
        #390 flip = 1;
        #10 flip = 0;
    end
    
    initial begin
        #430 flip = 1;
        #10 flip = 0;
    end

    initial begin
        #470 flip = 1;
        #10 flip = 0;
    end

    initial begin
        #460 enable = 0;
        #30 enable = 1;
    end

    initial begin
        #10 rst_n = 1;
        #90 rst_n = 0;
        #20 rst_n = 1;
        #90 rst_n = 0;
        #20 rst_n = 1;
        #90 rst_n = 0;
        #20 rst_n = 1;
    end

    initial begin
        #340 max = 3;
        #80 max = 2;
        #30 max = 3;
    end

    initial begin
        #390 min = 1;
        #10 min = 3;
        #20 min = 2;
        #30 min = 1;
    end

    initial begin
        #515 $finish;
    end

    initial begin
        $dumpfile("Parameterized_Ping_Pong_Counter_t.vcd");
        $dumpvars(0, Parameterized_Ping_Pong_Counter_t);
    end
endmodule

johnny/Lab3/Parameterized_Ping_Pong_Counter_t.vcd
$date
	Thu Oct 10 02:50:41 2024
$end
$version
	Icarus Verilog
$end
$timescale
	1ps
$end
$scope module Parameterized_Ping_Pong_Counter_t $end
$var wire 4 ! out [3:0] $end
$var wire 1 " direction $end
$var reg 1 # clk $end
$var reg 1 $ enable $end
$var reg 1 % flip $end
$var reg 4 & max [3:0] $end
$var reg 4 ' min [3:0] $end
$var reg 1 ( rst_n $end
$scope module PPPC $end
$var wire 1 # clk $end
$var wire 1 $ enable $end
$var wire 1 % flip $end
$var wire 4 ) max [3:0] $end
$var wire 4 * min [3:0] $end
$var wire 1 ( rst_n $end
$var reg 1 " direction $end
$var reg 4 + out [3:0] $end
$upscope $end
$upscope $end
$enddefinitions $end
#0
$dumpvars
bx +
b0 *
b100 )
0(
b0 '
b100 &
0%
1$
0#
x"
bx !
$end
#5000
1"
b0 !
b0 +
1#
#10000
0#
1(
#15000
b1 !
b1 +
1#
#20000
0#
#25000
b10 !
b10 +
1#
#30000
0#
#35000
b11 !
b11 +
1#
#40000
0#
#45000
b100 !
b100 +
1#
#50000
0#
#55000
0"
b11 !
b11 +
1#
#60000
0#
#65000
b10 !
b10 +
1#
#70000
0#
#75000
b1 !
b1 +
1#
#80000
0#
#85000
b0 !
b0 +
1#
#90000
0#
#95000
1"
b1 !
b1 +
1#
#100000
0#
0(
#105000
b0 !
b0 +
1#
#110000
0#
#115000
1#
#120000
0#
1(
#125000
b1 !
b1 +
1#
#130000
0#
#135000
b10 !
b10 +
1#
#140000
0#
#145000
b11 !
b11 +
1#
#150000
0#
1%
#155000
b10 !
b10 +
0"
1#
#160000
0#
0%
#165000
b1 !
b1 +
1#
#170000
0#
#175000
b0 !
b0 +
1#
#180000
0#
#185000
1"
b1 !
b1 +
1#
#190000
0#
#195000
b10 !
b10 +
1#
#200000
0#
#205000
b11 !
b11 +
1#
#210000
0#
0(
#215000
b0 !
b0 +
1#
#220000
0#
#225000
1#
#230000
0#
1(
#235000
b1 !
b1 +
1#
#240000
0#
#245000
b10 !
b10 +
1#
#250000
0#
#255000
b11 !
b11 +
1#
#260000
0#
1%
#265000
b10 !
b10 +
0"
1#
#270000
0#
0%
#275000
b1 !
b1 +
1#
#280000
0#
1%
#285000
b10 !
b10 +
1"
1#
#290000
0#
0%
#295000
b11 !
b11 +
1#
#300000
0#
#305000
b100 !
b100 +
1#
#310000
0#
#315000
0"
b11 !
b11 +
1#
#320000
0#
0(
#325000
1"
b0 !
b0 +
1#
#330000
0#
#335000
1#
#340000
0#
1(
b11 &
b11 )
#345000
b1 !
b1 +
1#
#350000
0#
#355000
b10 !
b10 +
1#
#360000
0#
#365000
b11 !
b11 +
1#
#370000
0#
#375000
0"
b10 !
b10 +
1#
#380000
0#
#385000
b1 !
b1 +
1#
#390000
0#
b1 '
b1 *
1%
#395000
1"
b10 !
b10 +
1#
#400000
0#
b11 '
b11 *
0%
#405000
1#
#410000
0#
#415000
1#
#420000
0#
b10 '
b10 *
b10 &
b10 )
#425000
1#
#430000
0#
1%
#435000
1#
#440000
0#
0%
#445000
1#
#450000
0#
b1 '
b1 *
b11 &
b11 )
#455000
b11 !
b11 +
1#
#460000
0#
0$
#465000
1#
#470000
0#
1%
#475000
1#
#480000
0#
0%
#485000
1#
#490000
0#
1$
#495000
0"
b10 !
b10 +
1#
#500000
0#
#505000
b1 !
b1 +
1#
#510000
0#
#515000
1"
b10 !
b10 +
1#
