johnny/Lab3/Lab3_Team1_Ping_Pong_Counter.v
`timescale 1ns/1ps

module Ping_Pong_Counter (clk, rst_n, enable, direction, out);
    input clk, rst_n;
    input enable;
    output reg direction;
    output [4-1:0] out;
    
    reg [3:0] out;

    always @(posedge clk) begin
        if(!rst_n) begin
            out <= 4'b0000;
            direction <= 1;
        end
        else begin
            if(!enable) begin
                out <= out;
                direction <= direction;
            end
            else begin
                if(direction == 1) begin
                    if(out == 15) begin
                        out <= out-1;
                        direction <= 0;
                    end
                    else begin
                        out <= out+1;
                        direction <= direction;
                    end
                end
                else begin
                    if(out == 0) begin
                        out <= out+1;
                        direction <= 1;
                    end
                    else begin
                        out <= out-1;
                        direction <= direction;
                    end
                end
            end
        end
    end
endmodule

johnny/Lab3/Lab3_Team1_Ping_Pong_Counter_t.v
`include "Lab3_Team1_Ping_Pong_Counter.v"
`timescale 1ns/1ps

module Ping_Pong_Counter_t ();
    reg clk = 1'b1;
    reg rst_n = 1'b0;
    wire direction;
    reg enable = 1'b1;
    wire [3:0] out;
    Ping_Pong_Counter PPC(clk, rst_n, enable, direction, out);
    
    always #5 clk = !clk;

    /*initial begin
        #10 rst_n = !rst_n;
        #(5*16*2*2) rst_n = !rst_n;
        #10 rst_n = !rst_n;
        #100 rst_n = !rst_n;
        #10 rst_n = !rst_n;
        #300 rst_n = !rst_n;
        #10 rst_n = !rst_n;
        #30 rst_n = !rst_n;
        #20 rst_n = !rst_n;
        
    end*/
    initial begin
        #20
        #(5*16*2*2) enable = !enable;
        #50 enable = !enable;
        #100 enable = !enable;
        #10 enable = !enable;
        $finish; 
    end

    initial begin
        #20 rst_n = !rst_n;
        #300 rst_n = !rst_n;
        #10 rst_n = !rst_n;
        #20 rst_n = !rst_n;
        #10 rst_n = !rst_n;
        #250 rst_n = !rst_n;
        #10 rst_n = !rst_n;
    end

    initial begin
        $dumpfile("Ping_Pong_Counter.vcd");
        $dumpvars(0, Ping_Pong_Counter_t);
    end
endmodule

johnny/Lab3/Ping_Pong_Counter.vcd
$date
	Thu Oct 10 02:49:52 2024
$end
$version
	Icarus Verilog
$end
$timescale
	1ps
$end
$scope module Ping_Pong_Counter_t $end
$var wire 4 ! out [3:0] $end
$var wire 1 " direction $end
$var reg 1 # clk $end
$var reg 1 $ enable $end
$var reg 1 % rst_n $end
$scope module PPC $end
$var wire 1 # clk $end
$var wire 1 $ enable $end
$var wire 1 % rst_n $end
$var reg 1 " direction $end
$var reg 4 & out [3:0] $end
$upscope $end
$upscope $end
$enddefinitions $end
#0
$dumpvars
b0 &
0%
1$
1#
1"
b0 !
$end
#5000
0#
#10000
1#
#15000
0#
#20000
b1 !
b1 &
1#
1%
#25000
0#
#30000
b10 !
b10 &
1#
#35000
0#
#40000
b11 !
b11 &
1#
#45000
0#
#50000
b100 !
b100 &
1#
#55000
0#
#60000
b101 !
b101 &
1#
#65000
0#
#70000
b110 !
b110 &
1#
#75000
0#
#80000
b111 !
b111 &
1#
#85000
0#
#90000
b1000 !
b1000 &
1#
#95000
0#
#100000
b1001 !
b1001 &
1#
#105000
0#
#110000
b1010 !
b1010 &
1#
#115000
0#
#120000
b1011 !
b1011 &
1#
#125000
0#
#130000
b1100 !
b1100 &
1#
#135000
0#
#140000
b1101 !
b1101 &
1#
#145000
0#
#150000
b1110 !
b1110 &
1#
#155000
0#
#160000
b1111 !
b1111 &
1#
#165000
0#
#170000
0"
b1110 !
b1110 &
1#
#175000
0#
#180000
b1101 !
b1101 &
1#
#185000
0#
#190000
b1100 !
b1100 &
1#
#195000
0#
#200000
b1011 !
b1011 &
1#
#205000
0#
#210000
b1010 !
b1010 &
1#
#215000
0#
#220000
b1001 !
b1001 &
1#
#225000
0#
#230000
b1000 !
b1000 &
1#
#235000
0#
#240000
b111 !
b111 &
1#
#245000
0#
#250000
b110 !
b110 &
1#
#255000
0#
#260000
b101 !
b101 &
1#
#265000
0#
#270000
b100 !
b100 &
1#
#275000
0#
#280000
b11 !
b11 &
1#
#285000
0#
#290000
b10 !
b10 &
1#
#295000
0#
#300000
b1 !
b1 &
1#
#305000
0#
#310000
b0 !
b0 &
1#
#315000
0#
#320000
1"
1#
0%
#325000
0#
#330000
b1 !
b1 &
1#
1%
#335000
0#
#340000
1#
0$
#345000
0#
#350000
b0 !
b0 &
1#
0%
#355000
0#
#360000
1#
1%
#365000
0#
#370000
1#
#375000
0#
#380000
1#
#385000
0#
#390000
b1 !
b1 &
1#
1$
#395000
0#
#400000
b10 !
b10 &
1#
#405000
0#
#410000
b11 !
b11 &
1#
#415000
0#
#420000
b100 !
b100 &
1#
#425000
0#
#430000
b101 !
b101 &
1#
#435000
0#
#440000
b110 !
b110 &
1#
#445000
0#
#450000
b111 !
b111 &
1#
#455000
0#
#460000
b1000 !
b1000 &
1#
#465000
0#
#470000
b1001 !
b1001 &
1#
#475000
0#
#480000
b1010 !
b1010 &
1#
#485000
0#
#490000
1#
0$
#495000
0#
#500000
b1011 !
b1011 &
1#
1$
