johnny/Lab3/Lab3_Team1_Round_Robin_FIFO_Arbiter.v
`timescale 1ns/1ps

module Round_Robin_FIFO_Arbiter(clk, rst_n, wen, a, b, c, d, dout, valid);
    input clk;
    input rst_n;
    input [4-1:0] wen;
    input [8-1:0] a, b, c, d;
    output [8-1:0] dout;
    output valid;

    reg [1:0] counter;
    wire [7:0] dout;
    wire [7:0] out[3:0];
    wire [3:0] error;
    wire valid;
    reg [1:0] sel;
    reg [1:0] dotcar;

    FIFO_8 FFA(clk, rst_n, wen[0], counter==0, a, out[0], error[0]);
    FIFO_8 FFB(clk, rst_n, wen[1], counter==1, b, out[1], error[1]);
    FIFO_8 FFC(clk, rst_n, wen[2], counter==2, c, out[2], error[2]);
    FIFO_8 FFD(clk, rst_n, wen[3], counter==3, d, out[3], error[3]);
    
    assign dout = (!clk ? dout : (!rst_n ? 0 : (!(error[sel]==1 || wen[sel]==1)) ? out[sel] : 0));
    assign valid = (!clk ? valid : (!rst_n ? 0 : (!(error[sel]==1 || wen[sel]==1)) ? 1 : 0));

    always @(posedge clk) begin
        sel <= counter;
    end

    always @(posedge clk) begin
        if(rst_n) counter <= counter +1;
        else counter <= 0;
    end

endmodule

module FIFO_8(clk, rst_n, wen, ren, din, dout, error);
    input clk;
    input rst_n;
    input wen, ren;
    input [8-1:0] din;
    output [8-1:0] dout;
    output error;

    reg [7:0] MEM[7:0];
    reg [3:0] COUNTER = 0; 
    reg [2:0] Waddr = 0, Raddr = 0;
    reg [8-1:0] dout;
    reg [8-1:0] dotcar;;
    reg error;

    always @(posedge clk) begin
        if(!rst_n) begin
            MEM[0] <= 0;
            MEM[1] <= 0;
            MEM[2] <= 0;
            MEM[3] <= 0;
            MEM[4] <= 0;
            MEM[5] <= 0;
            MEM[6] <= 0;
            MEM[7] <= 0;
            COUNTER <= 0;
            Waddr <= 0;
            Raddr <= 0;
            dout <= 0;
            error <= 0;
        end
        else begin
            if (wen == 1) begin
                if(COUNTER == 8) begin
                    dout <= dotcar;
                    COUNTER <= COUNTER;
                end
                else begin
                    dout <= dotcar;
                    MEM[Waddr] <= din;
                    Waddr <= Waddr + 1;
                    COUNTER <= COUNTER + 1;
                end
            end
            else if (ren == 1) begin
                if(COUNTER == 0) begin
                    dout <= dotcar;
                    COUNTER <= COUNTER;
                end
                else begin
                    dout <= MEM[Raddr];
                    Raddr <= Raddr + 1;
                    COUNTER <= COUNTER - 1;
                end
            end
            else begin
                dout <= dotcar;
                COUNTER <= COUNTER;
            end
        end
    end    
    always @(posedge clk) begin
        error <= (COUNTER==0 && wen==0 && ren==1)||(COUNTER==8 && wen==1);
    end
endmodule

johnny/Lab3/Lab3_Team1_Round_Robin_FIFO_Arbiter_t.v
`include "Lab3_Team1_Round_Robin_FIFO_Arbiter.v"
`timescale 1ns/1ps

module Round_Robin_FIFO_Arbiter_t ();
    reg clk = 0, rst_n = 0;
    reg [3:0] wen;
    reg [8-1:0] a, b, c, d;
    wire [8-1:0] dout;
    wire valid;

    Round_Robin_FIFO_Arbiter RR(clk, rst_n, wen, a, b, c, d, dout, valid);

    always #5 clk = !clk;
    initial begin
        #10 rst_n = !rst_n;
    end
    initial begin
        wen = 4'b1111;
        #20 wen = 4'b1000;
        #10 wen = 4'b0100;
        #10 wen = 4'b0000;
        #30 wen = 4'b0001;
        #10 wen = 4'b0000;
        #40 wen = 4'b1111;
        #10 wen = 4'b0000;
        #50 $finish;
    end
    initial begin
        #10
        a = 87;
        b = 56;
        c = 9;
        d = 13;
        #10
        d = 85;
        a = 0;
        b = 0;
        c = 0;
        #10
        c = 139;
        d = 0;
        #10
        c = 0;
        #30
        a = 51;
        #50
        a = 1;
        b = 2;
        c = 3;
        d = 4;
        rst_n = !rst_n;
        #10
        a = 0;
        b = 0;
        c = 0;
        d = 0;
        rst_n = !rst_n;
    end
    initial begin
        $dumpfile("Round_Robin_FIFO_Arbiter_t.vcd");
        $dumpvars(0, Round_Robin_FIFO_Arbiter_t);
    end
endmodule

johnny/Lab3/Round_Robin_FIFO_Arbiter_t.vcd
$date
	Thu Oct 10 00:57:31 2024
$end
$version
	Icarus Verilog
$end
$timescale
	1ps
$end
$scope module Round_Robin_FIFO_Arbiter_t $end
$var wire 1 ! valid $end
$var wire 8 " dout [7:0] $end
$var reg 8 # a [7:0] $end
$var reg 8 $ b [7:0] $end
$var reg 8 % c [7:0] $end
$var reg 1 & clk $end
$var reg 8 ' d [7:0] $end
$var reg 1 ( rst_n $end
$var reg 4 ) wen [3:0] $end
$scope module RR $end
$var wire 8 * a [7:0] $end
$var wire 8 + b [7:0] $end
$var wire 8 , c [7:0] $end
$var wire 1 & clk $end
$var wire 8 - d [7:0] $end
$var wire 1 ( rst_n $end
$var wire 4 . wen [3:0] $end
$var wire 1 ! valid $end
$var wire 4 / error [3:0] $end
$var wire 8 0 dout [7:0] $end
$var reg 2 1 counter [1:0] $end
$var reg 2 2 sel [1:0] $end
$scope module FFA $end
$var wire 1 & clk $end
$var wire 8 3 din [7:0] $end
$var wire 1 4 ren $end
$var wire 1 ( rst_n $end
$var wire 1 5 wen $end
$var reg 4 6 COUNTER [3:0] $end
$var reg 3 7 Raddr [2:0] $end
$var reg 3 8 Waddr [2:0] $end
$var reg 8 9 dotcar [7:0] $end
$var reg 8 : dout [7:0] $end
$var reg 1 ; error $end
$upscope $end
$scope module FFB $end
$var wire 1 & clk $end
$var wire 8 < din [7:0] $end
$var wire 1 = ren $end
$var wire 1 ( rst_n $end
$var wire 1 > wen $end
$var reg 4 ? COUNTER [3:0] $end
$var reg 3 @ Raddr [2:0] $end
$var reg 3 A Waddr [2:0] $end
$var reg 8 B dotcar [7:0] $end
$var reg 8 C dout [7:0] $end
$var reg 1 D error $end
$upscope $end
$scope module FFC $end
$var wire 1 & clk $end
$var wire 8 E din [7:0] $end
$var wire 1 F ren $end
$var wire 1 ( rst_n $end
$var wire 1 G wen $end
$var reg 4 H COUNTER [3:0] $end
$var reg 3 I Raddr [2:0] $end
$var reg 3 J Waddr [2:0] $end
$var reg 8 K dotcar [7:0] $end
$var reg 8 L dout [7:0] $end
$var reg 1 M error $end
$upscope $end
$scope module FFD $end
$var wire 1 & clk $end
$var wire 8 N din [7:0] $end
$var wire 1 O ren $end
$var wire 1 ( rst_n $end
$var wire 1 P wen $end
$var reg 4 Q COUNTER [3:0] $end
$var reg 3 R Raddr [2:0] $end
$var reg 3 S Waddr [2:0] $end
$var reg 8 T dotcar [7:0] $end
$var reg 8 U dout [7:0] $end
$var reg 1 V error $end
$upscope $end
$upscope $end
$upscope $end
$enddefinitions $end
#0
$dumpvars
xV
bx U
bx T
b0 S
b0 R
b0 Q
1P
xO
bx N
xM
bx L
bx K
b0 J
b0 I
b0 H
1G
xF
bx E
xD
bx C
bx B
b0 A
b0 @
b0 ?
1>
x=
bx <
x;
bx :
bx 9
b0 8
b0 7
b0 6
15
x4
bx 3
bx 2
bx 1
bx 0
bx /
b1111 .
bx -
bx ,
bx +
bx *
b1111 )
0(
bx '
0&
bx %
bx $
bx #
bx "
z!
$end
#5000
b0 :
0;
b0 C
0D
b0 L
0M
b0 U
b0 /
0V
14
0=
0F
0O
b0 1
0!
b0 "
b0 0
1&
#10000
0&
b1101 '
b1101 -
b1101 N
b1001 %
b1001 ,
b1001 E
b111000 $
b111000 +
b111000 <
b1010111 #
b1010111 *
b1010111 3
1(
#15000
04
1=
b1 1
b0 2
b1 Q
b1 S
bx U
b1 H
b1 J
bx L
b1 ?
b1 A
bx C
b1 6
b1 8
bx :
0!
b0 "
b0 0
1&
#20000
05
0>
0G
0&
b0 %
b0 ,
b0 E
b0 $
b0 +
b0 <
b0 #
b0 *
b0 3
b1010101 '
b1010101 -
b1010101 N
b1000 )
b1000 .
#25000
b0 ?
b1 @
b111000 C
b10 Q
b10 S
b1 2
0=
1F
b10 1
1!
b111000 "
b111000 0
1&
#30000
1G
0P
0&
b0 '
b0 -
b0 N
b10001011 %
b10001011 ,
b10001011 E
b100 )
b100 .
#35000
0!
b0 "
b0 0
0F
1O
b11 1
b10 2
b10 H
b10 J
bx C
1&
#40000
0G
0&
b0 %
b0 ,
b0 E
b0 )
b0 .
#45000
b1 Q
b1 R
b1101 U
b11 2
14
0O
b0 1
1!
b1101 "
b1101 0
1&
#50000
0&
#55000
b1010111 "
b1010111 0
04
1=
b1 1
b0 2
bx U
b0 6
b1 7
b1010111 :
1&
#60000
0&
#65000
0!
b0 "
b0 0
bx :
b10 /
1D
b1 2
0=
1F
b10 1
1&
#70000
15
0&
b110011 #
b110011 *
b110011 3
b1 )
b1 .
#75000
1!
b1001 "
b1001 0
0F
1O
b11 1
b10 2
b1 H
b1 I
b1001 L
b0 /
0D
b1 6
b10 8
1&
#80000
05
0&
b0 )
b0 .
#85000
b1010101 "
b1010101 0
bx L
b0 Q
b10 R
b1010101 U
b11 2
14
0O
b0 1
1&
#90000
0&
#95000
b110011 "
b110011 0
04
1=
b1 1
b0 2
bx U
b0 6
b10 7
b110011 :
1&
#100000
0&
#105000
0!
b0 "
b0 0
bx :
b10 /
1D
b1 2
0=
1F
b10 1
1&
#110000
0&
#115000
1!
b10001011 "
b10001011 0
0F
1O
b11 1
b10 2
b0 H
b10 I
b10001011 L
b0 /
0D
1&
#120000
15
1>
1G
1P
0&
b1111 )
b1111 .
0(
b100 '
b100 -
b100 N
b11 %
b11 ,
b11 E
b10 $
b10 +
b10 <
b1 #
b1 *
b1 3
#125000
b0 :
b0 7
b0 8
b0 C
b0 @
b0 A
b0 L
b0 I
b0 J
b0 U
b0 R
b0 S
b11 2
14
0O
b0 1
0!
b0 "
b0 0
1&
#130000
05
0>
0G
0P
0&
b0 )
b0 .
1(
b0 '
b0 -
b0 N
b0 %
b0 ,
b0 E
b0 $
b0 +
b0 <
b0 #
b0 *
b0 3
#135000
b0 "
b0 0
04
1=
b1 1
b0 2
bx U
bx L
bx C
b1 /
1;
bx :
0!
1&
#140000
0&
#145000
0;
b10 /
1D
b1 2
0=
1F
b10 1
1&
#150000
0&
#155000
0F
1O
b11 1
b10 2
1M
b100 /
0D
1&
#160000
0&
#165000
0M
b1000 /
1V
b11 2
14
0O
b0 1
1&
#170000
0&
#175000
04
1=
b1 1
b0 2
0V
b1 /
1;
1&
