roger/Lab2/a5_Exhausted_Testing.v
`timescale 1ns/1ps

module Exhausted_Testing(a, b, cin, error, done);
    output [4-1:0] a, b;
    output cin;
    output error;
    output done;

    // input signal to the test instance.
    reg [4-1:0] a = 4'b0000;
    reg [4-1:0] b = 4'b0000;
    reg cin = 1'b0;

    // initial value for the done and error indicator: not done, no error
    reg done = 1'b0;
    reg error = 1'b0;


    // output from the test instance.
    wire [4-1:0] sum;
    wire cout;

    // instantiate the test instance.
    Ripple_Carry_Adder rca(
        .a (a), 
        .b (b), 
        .cin (cin),
        .cout (cout),
        .sum (sum)
    );

    initial begin
        repeat(2) begin
            repeat (2**4) begin
                repeat (2**4-1) begin
                    #1
                    error = ({cout, sum} != a+b+cin);
                    #4
                    b = b + 4'b1;
                end
                #1
                error = ({cout, sum} != a+b+cin);
                #4
                a = a + 4'b1;
                b = 4'b0;
            end
            cin = !cin;
        end
        done = 1'b1;
        #1 error = ({cout, sum} != a+b+cin);
        #4 done = 1'b0;
    end


    initial begin
        $dumpfile("a5.vcd");
        $dumpvars(0, Exhausted_Testing);
    end
endmodule

module Ripple_Carry_Adder(a, b, cin, cout, sum);
    input [4-1:0] a, b;
    input cin;
    output cout;
    output [4-1:0] sum;
    
    wire c1, c2, c3;

    Full_Adder FA0(a[0], b[0], cin, c1, sum[0]);
    Full_Adder FA1(a[1], b[1], c1, c2, sum[1]);
    Full_Adder FA2(a[2], b[2], c2, c3, sum[2]);
    Full_Adder FA3(a[3], b[3], c3, cout, sum[3]);
endmodule

// ---- ---- COPY ---- ----

module Full_Adder (a, b, cin, cout, sum);
    input a, b, cin;
    output cout, sum;

    wire con1;

    XOR_w_NAND XOR1 (con1, a, b);
    XOR_w_NAND XOR2 (sum, cin, con1);
    Majority MJ1 (a, b, cin, cout);
endmodule

// ---- ---- COPY ---- ----

module Majority(a, b, c, out);
    input a, b, c;
    output out;

    wire con1, con2, con3, con4;

    AND_w_NAND AND1 (con1, a, b);
    AND_w_NAND AND2 (con2, a, c);
    OR_w_NAND OR1 (con3, con1, con2);
    AND_w_NAND AND4 (con4, b, c);
    OR_w_NAND OR2 (out, con3, con4);
endmodule

// ---- ---- COPY ---- ----

module AND_w_NAND (out, a, b);
    input a, b;
    output out;
    wire con1;
    nand NAND1(con1, a, b);
    nand NAND2(out, con1, con1);
endmodule

module OR_w_NAND (out, a, b);
    input a, b;
    output out;
    wire con1, con2;
    nand NAND1(con1, a, a);
    nand NAND2(con2, b, b);
    nand NAND3(out, con1, con2);
endmodule

module XOR_w_NAND (out, a, b);
    input a, b;
    output out;
    wire con1, con2, con3;
    nand NAND1(con1, a, b);
    nand NAND2(con2, a, con1);
    nand NAND3(con3, b, con1);
    nand NAND4(out, con2, con3);
endmodule

roger/Lab2/a5.vcd
$date
	Wed Oct 16 22:22:42 2024
$end
$version
	Icarus Verilog
$end
$timescale
	1ps
$end
$scope module Exhausted_Testing $end
$var wire 4 ! sum [3:0] $end
$var wire 1 " cout $end
$var reg 4 # a [3:0] $end
$var reg 4 $ b [3:0] $end
$var reg 1 % cin $end
$var reg 1 & done $end
$var reg 1 ' error $end
$scope module rca $end
$var wire 4 ( a [3:0] $end
$var wire 4 ) b [3:0] $end
$var wire 1 % cin $end
$var wire 4 * sum [3:0] $end
$var wire 1 " cout $end
$var wire 1 + c3 $end
$var wire 1 , c2 $end
$var wire 1 - c1 $end
$scope module FA0 $end
$var wire 1 . a $end
$var wire 1 / b $end
$var wire 1 % cin $end
$var wire 1 0 sum $end
$var wire 1 - cout $end
$var wire 1 1 con1 $end
$scope module MJ1 $end
$var wire 1 . a $end
$var wire 1 / b $end
$var wire 1 % c $end
$var wire 1 - out $end
$var wire 1 2 con4 $end
$var wire 1 3 con3 $end
$var wire 1 4 con2 $end
$var wire 1 5 con1 $end
$scope module AND1 $end
$var wire 1 . a $end
$var wire 1 / b $end
$var wire 1 6 con1 $end
$var wire 1 5 out $end
$upscope $end
$scope module AND2 $end
$var wire 1 . a $end
$var wire 1 % b $end
$var wire 1 7 con1 $end
$var wire 1 4 out $end
$upscope $end
$scope module AND4 $end
$var wire 1 / a $end
$var wire 1 % b $end
$var wire 1 8 con1 $end
$var wire 1 2 out $end
$upscope $end
$scope module OR1 $end
$var wire 1 5 a $end
$var wire 1 4 b $end
$var wire 1 9 con1 $end
$var wire 1 : con2 $end
$var wire 1 3 out $end
$upscope $end
$scope module OR2 $end
$var wire 1 3 a $end
$var wire 1 2 b $end
$var wire 1 ; con1 $end
$var wire 1 < con2 $end
$var wire 1 - out $end
$upscope $end
$upscope $end
$scope module XOR1 $end
$var wire 1 . a $end
$var wire 1 / b $end
$var wire 1 = con1 $end
$var wire 1 > con2 $end
$var wire 1 ? con3 $end
$var wire 1 1 out $end
$upscope $end
$scope module XOR2 $end
$var wire 1 % a $end
$var wire 1 1 b $end
$var wire 1 @ con1 $end
$var wire 1 A con2 $end
$var wire 1 B con3 $end
$var wire 1 0 out $end
$upscope $end
$upscope $end
$scope module FA1 $end
$var wire 1 C a $end
$var wire 1 D b $end
$var wire 1 - cin $end
$var wire 1 E sum $end
$var wire 1 , cout $end
$var wire 1 F con1 $end
$scope module MJ1 $end
$var wire 1 C a $end
$var wire 1 D b $end
$var wire 1 - c $end
$var wire 1 , out $end
$var wire 1 G con4 $end
$var wire 1 H con3 $end
$var wire 1 I con2 $end
$var wire 1 J con1 $end
$scope module AND1 $end
$var wire 1 C a $end
$var wire 1 D b $end
$var wire 1 K con1 $end
$var wire 1 J out $end
$upscope $end
$scope module AND2 $end
$var wire 1 C a $end
$var wire 1 - b $end
$var wire 1 L con1 $end
$var wire 1 I out $end
$upscope $end
$scope module AND4 $end
$var wire 1 D a $end
$var wire 1 - b $end
$var wire 1 M con1 $end
$var wire 1 G out $end
$upscope $end
$scope module OR1 $end
$var wire 1 J a $end
$var wire 1 I b $end
$var wire 1 N con1 $end
$var wire 1 O con2 $end
$var wire 1 H out $end
$upscope $end
$scope module OR2 $end
$var wire 1 H a $end
$var wire 1 G b $end
$var wire 1 P con1 $end
$var wire 1 Q con2 $end
$var wire 1 , out $end
$upscope $end
$upscope $end
$scope module XOR1 $end
$var wire 1 C a $end
$var wire 1 D b $end
$var wire 1 R con1 $end
$var wire 1 S con2 $end
$var wire 1 T con3 $end
$var wire 1 F out $end
$upscope $end
$scope module XOR2 $end
$var wire 1 - a $end
$var wire 1 F b $end
$var wire 1 U con1 $end
$var wire 1 V con2 $end
$var wire 1 W con3 $end
$var wire 1 E out $end
$upscope $end
$upscope $end
$scope module FA2 $end
$var wire 1 X a $end
$var wire 1 Y b $end
$var wire 1 , cin $end
$var wire 1 Z sum $end
$var wire 1 + cout $end
$var wire 1 [ con1 $end
$scope module MJ1 $end
$var wire 1 X a $end
$var wire 1 Y b $end
$var wire 1 , c $end
$var wire 1 + out $end
$var wire 1 \ con4 $end
$var wire 1 ] con3 $end
$var wire 1 ^ con2 $end
$var wire 1 _ con1 $end
$scope module AND1 $end
$var wire 1 X a $end
$var wire 1 Y b $end
$var wire 1 ` con1 $end
$var wire 1 _ out $end
$upscope $end
$scope module AND2 $end
$var wire 1 X a $end
$var wire 1 , b $end
$var wire 1 a con1 $end
$var wire 1 ^ out $end
$upscope $end
$scope module AND4 $end
$var wire 1 Y a $end
$var wire 1 , b $end
$var wire 1 b con1 $end
$var wire 1 \ out $end
$upscope $end
$scope module OR1 $end
$var wire 1 _ a $end
$var wire 1 ^ b $end
$var wire 1 c con1 $end
$var wire 1 d con2 $end
$var wire 1 ] out $end
$upscope $end
$scope module OR2 $end
$var wire 1 ] a $end
$var wire 1 \ b $end
$var wire 1 e con1 $end
$var wire 1 f con2 $end
$var wire 1 + out $end
$upscope $end
$upscope $end
$scope module XOR1 $end
$var wire 1 X a $end
$var wire 1 Y b $end
$var wire 1 g con1 $end
$var wire 1 h con2 $end
$var wire 1 i con3 $end
$var wire 1 [ out $end
$upscope $end
$scope module XOR2 $end
$var wire 1 , a $end
$var wire 1 [ b $end
$var wire 1 j con1 $end
$var wire 1 k con2 $end
$var wire 1 l con3 $end
$var wire 1 Z out $end
$upscope $end
$upscope $end
$scope module FA3 $end
$var wire 1 m a $end
$var wire 1 n b $end
$var wire 1 + cin $end
$var wire 1 o sum $end
$var wire 1 " cout $end
$var wire 1 p con1 $end
$scope module MJ1 $end
$var wire 1 m a $end
$var wire 1 n b $end
$var wire 1 + c $end
$var wire 1 " out $end
$var wire 1 q con4 $end
$var wire 1 r con3 $end
$var wire 1 s con2 $end
$var wire 1 t con1 $end
$scope module AND1 $end
$var wire 1 m a $end
$var wire 1 n b $end
$var wire 1 u con1 $end
$var wire 1 t out $end
$upscope $end
$scope module AND2 $end
$var wire 1 m a $end
$var wire 1 + b $end
$var wire 1 v con1 $end
$var wire 1 s out $end
$upscope $end
$scope module AND4 $end
$var wire 1 n a $end
$var wire 1 + b $end
$var wire 1 w con1 $end
$var wire 1 q out $end
$upscope $end
$scope module OR1 $end
$var wire 1 t a $end
$var wire 1 s b $end
$var wire 1 x con1 $end
$var wire 1 y con2 $end
$var wire 1 r out $end
$upscope $end
$scope module OR2 $end
$var wire 1 r a $end
$var wire 1 q b $end
$var wire 1 z con1 $end
$var wire 1 { con2 $end
$var wire 1 " out $end
$upscope $end
$upscope $end
$scope module XOR1 $end
$var wire 1 m a $end
$var wire 1 n b $end
$var wire 1 | con1 $end
$var wire 1 } con2 $end
$var wire 1 ~ con3 $end
$var wire 1 p out $end
$upscope $end
$scope module XOR2 $end
$var wire 1 + a $end
$var wire 1 p b $end
$var wire 1 !" con1 $end
$var wire 1 "" con2 $end
$var wire 1 #" con3 $end
$var wire 1 o out $end
$upscope $end
$upscope $end
$upscope $end
$upscope $end
$enddefinitions $end
$comment Show the parameter values. $end
$dumpall
$end
#0
$dumpvars
1#"
1""
1!"
1~
1}
1|
1{
1z
1y
1x
1w
1v
1u
0t
0s
0r
0q
0p
0o
0n
0m
1l
1k
1j
1i
1h
1g
1f
1e
1d
1c
1b
1a
1`
0_
0^
0]
0\
0[
0Z
0Y
0X
1W
1V
1U
1T
1S
1R
1Q
1P
1O
1N
1M
1L
1K
0J
0I
0H
0G
0F
0E
0D
0C
1B
1A
1@
1?
1>
1=
1<
1;
1:
19
18
17
16
05
04
03
02
01
00
0/
0.
0-
0,
0+
b0 *
b0 )
b0 (
0'
0&
0%
b0 $
b0 #
0"
b0 !
$end
#5000
b1 !
b1 *
10
0B
11
0?
1/
b1 $
b1 )
#10000
00
b10 !
b10 *
1E
1B
0W
01
1F
1?
0T
0/
1D
b10 $
b10 )
#15000
b11 !
b11 *
10
0B
11
0?
1/
b11 $
b11 )
#20000
00
0E
b100 !
b100 *
1Z
1B
1W
0l
01
0F
1[
1?
1T
0i
0/
0D
1Y
b100 $
b100 )
#25000
b101 !
b101 *
10
0B
11
0?
1/
b101 $
b101 )
#30000
00
b110 !
b110 *
1E
1B
0W
01
1F
1?
0T
0/
1D
b110 $
b110 )
#35000
b111 !
b111 *
10
0B
11
0?
1/
b111 $
b111 )
#40000
00
0E
0Z
b1000 !
b1000 *
1o
1B
1W
1l
0#"
01
0F
0[
1p
1?
1T
1i
0~
0/
0D
0Y
1n
b1000 $
b1000 )
#45000
b1001 !
b1001 *
10
0B
11
0?
1/
b1001 $
b1001 )
#50000
00
b1010 !
b1010 *
1E
1B
0W
01
1F
1?
0T
0/
1D
b1010 $
b1010 )
#55000
b1011 !
b1011 *
10
0B
11
0?
1/
b1011 $
b1011 )
#60000
00
0E
b1100 !
b1100 *
1Z
1B
1W
0l
01
0F
1[
1?
1T
0i
0/
0D
1Y
b1100 $
b1100 )
#65000
b1101 !
b1101 *
10
0B
11
0?
1/
b1101 $
b1101 )
#70000
00
b1110 !
b1110 *
1E
1B
0W
01
1F
1?
0T
0/
1D
b1110 $
b1110 )
#75000
b1111 !
b1111 *
10
0B
11
0?
1/
b1111 $
b1111 )
#80000
0E
0Z
b1 !
b1 *
0o
1W
1l
1#"
0F
0[
0p
1?
1T
1i
1~
0>
0/
0D
0Y
0n
1.
b0 $
b0 )
b1 #
b1 (
#85000
1E
0V
1-
0;
b10 !
b10 *
00
13
1B
09
01
15
1>
06
0=
1?
1/
b1 $
b1 )
#90000
0-
0Z
1;
10
1k
b11 !
b11 *
1E
03
0B
0,
1V
19
11
1Q
1U
0W
05
0>
0G
1F
16
1=
1M
0T
0/
1D
b10 $
b10 )
#95000
1Z
0k
1,
0Q
0E
1G
1W
0M
0U
1V
1-
0;
b100 !
b100 *
00
13
1B
09
01
15
1>
06
0=
1?
1/
b11 $
b11 )
#100000
0-
0o
1;
10
0E
1""
b101 !
b101 *
1Z
03
0B
0,
1V
0+
1k
19
11
1Q
1U
1f
1j
0l
05
0>
0G
0F
0\
1[
16
1=
1M
1T
1b
0i
0/
0D
1Y
b100 $
b100 )
#105000
1E
0V
1-
0;
b110 !
b110 *
00
13
1B
09
01
15
1>
06
0=
1?
1/
b101 $
b101 )
#110000
0o
1""
0+
1f
1Z
0-
0\
0l
1;
10
1b
1j
1k
b111 !
b111 *
1E
03
0B
0,
1V
19
11
1Q
1U
0W
05
0>
0G
1F
16
1=
1M
0T
0/
1D
b110 $
b110 )
#115000
1o
0""
1+
0f
0Z
1\
1l
0b
0j
1k
1,
0Q
0E
1G
1W
0M
0U
1V
1-
0;
b1000 !
b1000 *
00
13
1B
09
01
15
1>
06
0=
1?
1/
b111 $
b111 )
#120000
0-
1;
10
0E
0Z
b1001 !
b1001 *
1o
03
0B
0,
1V
0+
1k
0"
1""
19
11
1Q
1U
1f
1j
1{
1!"
0#"
05
0>
0G
0F
0\
0[
0q
1p
16
1=
1M
1T
1b
1i
1w
0~
0/
0D
0Y
1n
b1000 $
b1000 )
#125000
1E
0V
1-
0;
b1010 !
b1010 *
00
13
1B
09
01
15
1>
06
0=
1?
1/
b1001 $
b1001 )
#130000
0-
0Z
1;
10
1k
b1011 !
b1011 *
1E
03
0B
0,
1V
19
11
1Q
1U
0W
05
0>
0G
1F
16
1=
1M
0T
0/
1D
b1010 $
b1010 )
#135000
1Z
0k
1,
0Q
0E
1G
1W
0M
0U
1V
1-
0;
b1100 !
b1100 *
00
13
1B
09
01
15
1>
06
0=
1?
1/
b1011 $
b1011 )
#140000
0"
1{
1o
0-
0q
0#"
1;
10
0E
1w
1!"
1""
b1101 !
b1101 *
1Z
03
0B
0,
1V
0+
1k
19
11
1Q
1U
1f
1j
0l
05
0>
0G
0F
0\
1[
16
1=
1M
1T
1b
0i
0/
0D
1Y
b1100 $
b1100 )
#145000
1E
0V
1-
0;
b1110 !
b1110 *
00
13
1B
09
01
15
1>
06
0=
1?
1/
b1101 $
b1101 )
#150000
0"
1{
1o
0q
0#"
1w
1!"
1""
0+
1f
1Z
0-
0\
0l
1;
10
1b
1j
1k
b1111 !
b1111 *
1E
03
0B
0,
1V
19
11
1Q
1U
0W
05
0>
0G
1F
16
1=
1M
0T
0/
1D
b1110 $
b1110 )
#155000
1"
0{
0o
1q
1#"
0w
0!"
1""
1+
0f
0Z
1\
1l
0b
0j
1k
1,
0Q
0E
1G
1W
0M
0U
1V
1-
0;
b0 !
b0 *
00
13
1B
09
01
15
1>
06
0=
1?
1/
b1111 $
b1111 )
#160000
1E
0W
1U
0-
0Z
b10 !
b10 *
0o
1;
1P
0,
0+
1k
0"
1""
03
0H
1Q
1f
1j
1{
1!"
19
1O
0G
0\
0[
0q
0p
05
0I
1M
1T
1b
1i
1w
1~
16
1=
1L
0S
0/
0D
0Y
0n
0.
1C
b0 $
b0 )
b10 #
b10 (
#165000
b11 !
b11 *
10
0B
11
0?
1/
b1 $
b1 )
#170000
1Z
0k
1,
0P
0E
b100 !
b100 *
00
1H
1W
1B
0N
0F
01
1J
1S
1?
0K
0R
1T
0/
1D
b10 $
b10 )
#175000
b101 !
b101 *
10
0B
11
0?
1/
b11 $
b11 )
#180000
0,
0o
1P
1E
1""
1Z
b110 !
b110 *
00
0H
0W
0+
1k
1B
1N
1F
1f
1j
0l
01
0J
0S
0\
1[
1?
1K
1R
1b
0i
0/
0D
1Y
b100 $
b100 )
#185000
b111 !
b111 *
10
0B
11
0?
1/
b101 $
b101 )
#190000
1o
0""
1+
0f
0Z
1\
1l
0b
0j
1k
1,
0P
0E
b1000 !
b1000 *
00
1H
1W
1B
0N
0F
01
1J
1S
1?
0K
0R
1T
0/
1D
b110 $
b110 )
#195000
b1001 !
b1001 *
10
0B
11
0?
1/
b111 $
b111 )
#200000
0,
1P
1E
0Z
1o
b1010 !
b1010 *
00
0H
0W
0+
1k
0"
1""
1B
1N
1F
1f
1j
1{
1!"
0#"
01
0J
0S
0\
0[
0q
1p
1?
1K
1R
1b
1i
1w
0~
0/
0D
0Y
1n
b1000 $
b1000 )
#205000
b1011 !
b1011 *
10
0B
11
0?
1/
b1001 $
b1001 )
#210000
1Z
0k
1,
0P
0E
b1100 !
b1100 *
00
1H
1W
1B
0N
0F
01
1J
1S
1?
0K
0R
1T
0/
1D
b1010 $
b1010 )
#215000
b1101 !
b1101 *
10
0B
11
0?
1/
b1011 $
b1011 )
#220000
0"
1{
1o
0,
0q
0#"
1P
1E
1w
1!"
1""
1Z
b1110 !
b1110 *
00
0H
0W
0+
1k
1B
1N
1F
1f
1j
0l
01
0J
0S
0\
1[
1?
1K
1R
1b
0i
0/
0D
1Y
b1100 $
b1100 )
#225000
b1111 !
b1111 *
10
0B
11
0?
1/
b1101 $
b1101 )
#230000
1"
0{
0o
1q
1#"
0w
0!"
1""
1+
0f
0Z
1\
1l
0b
0j
1k
1,
0P
0E
b0 !
b0 *
00
1H
1W
1B
0N
0F
01
1J
1S
1?
0K
0R
1T
0/
1D
b1110 $
b1110 )
#235000
b1 !
b1 *
10
0B
11
0?
1/
b1111 $
b1111 )
#240000
0,
1P
1E
0Z
b11 !
b11 *
0o
0H
0W
0+
1k
0"
1""
1N
1F
1f
1j
1{
1!"
0J
0S
0\
0[
0q
0p
1?
1K
1R
1b
1i
1w
1~
0>
0/
0D
0Y
0n
1.
b0 $
b0 )
b11 #
b11 (
#245000
1Z
0k
1,
0P
1H
0O
0E
1I
1W
0L
0U
1V
1-
0;
b100 !
b100 *
00
13
1B
09
01
15
1>
06
0=
1?
1/
b1 $
b1 )
#250000
1O
0I
1L
0-
0E
1;
b101 !
b101 *
10
1V
03
0B
1U
19
11
0N
1Q
0F
05
0>
1J
0G
1S
16
1=
0K
1M
0R
1T
0/
1D
b10 $
b10 )
#255000
0O
0Q
1I
1G
1E
0L
0M
0V
1-
0;
b110 !
b110 *
00
13
1B
09
01
15
1>
06
0=
1?
1/
b11 $
b11 )
#260000
0,
1P
0H
1O
0I
1L
0-
1E
0o
1;
10
1V
1""
b111 !
b111 *
1Z
03
0B
1U
0W
0+
1k
19
11
1N
1Q
1F
1f
1j
0l
05
0>
0J
0G
0S
0\
1[
16
1=
1K
1M
1R
1b
0i
0/
0D
1Y
b100 $
b100 )
#265000
1o
0""
1+
0f
0Z
1\
1l
0b
0j
1k
1,
0P
1H
0O
0E
1I
1W
0L
0U
1V
1-
0;
b1000 !
b1000 *
00
13
1B
09
01
15
1>
06
0=
1?
1/
b101 $
b101 )
#270000
1O
0I
1L
0-
0E
1;
b1001 !
b1001 *
10
1V
03
0B
1U
19
11
0N
1Q
0F
05
0>
1J
0G
1S
16
1=
0K
1M
0R
1T
0/
1D
b110 $
b110 )
#275000
0O
0Q
1I
1G
1E
0L
0M
0V
1-
0;
b1010 !
b1010 *
00
13
1B
09
01
15
1>
06
0=
1?
1/
b111 $
b111 )
#280000
0,
1P
0H
1O
0I
1L
0-
1E
1;
10
1V
0Z
b1011 !
b1011 *
1o
03
0B
1U
0W
0+
1k
0"
1""
19
11
1N
1Q
1F
1f
1j
1{
1!"
0#"
05
0>
0J
0G
0S
0\
0[
0q
1p
16
1=
1K
1M
1R
1b
1i
1w
0~
0/
0D
0Y
1n
b1000 $
b1000 )
#285000
1Z
0k
1,
0P
1H
0O
0E
1I
1W
0L
0U
1V
1-
0;
b1100 !
b1100 *
00
13
1B
09
01
15
1>
06
0=
1?
1/
b1001 $
b1001 )
#290000
1O
0I
1L
0-
0E
1;
b1101 !
b1101 *
10
1V
03
0B
1U
19
11
0N
1Q
0F
05
0>
1J
0G
1S
16
1=
0K
1M
0R
1T
0/
1D
b1010 $
b1010 )
#295000
0O
0Q
1I
1G
1E
0L
0M
0V
1-
0;
b1110 !
b1110 *
00
13
1B
09
01
15
1>
06
0=
1?
1/
b1011 $
b1011 )
#300000
0,
1P
0H
1O
0I
0"
1L
1{
1o
0-
1E
0q
0#"
1;
10
1V
1w
1!"
1""
b1111 !
b1111 *
1Z
03
0B
1U
0W
0+
1k
19
11
1N
1Q
1F
1f
1j
0l
05
0>
0J
0G
0S
0\
1[
16
1=
1K
1M
1R
1b
0i
0/
0D
1Y
b1100 $
b1100 )
#305000
1"
0{
0o
1q
1#"
0w
0!"
1""
1+
0f
0Z
1\
1l
0b
0j
1k
1,
0P
1H
0O
0E
1I
1W
0L
0U
1V
1-
0;
b0 !
b0 *
00
13
1B
09
01
15
1>
06
0=
1?
1/
b1101 $
b1101 )
#310000
1O
0I
1L
0-
0E
1;
b1 !
b1 *
10
1V
03
0B
1U
19
11
0N
1Q
0F
05
0>
1J
0G
1S
16
1=
0K
1M
0R
1T
0/
1D
b1110 $
b1110 )
#315000
0O
0Q
1I
1G
1E
0L
0M
0V
1-
0;
b10 !
b10 *
00
13
1B
09
01
15
1>
06
0=
1?
1/
b1111 $
b1111 )
#320000
1Z
0E
0l
1V
1j
0-
0,
b100 !
b100 *
0o
1;
1P
1e
0+
0"
1""
03
0H
0]
1Q
1f
1{
1!"
19
1N
1O
1d
0G
0\
0q
0p
05
0J
0I
0^
1M
1b
1i
1w
1~
16
1=
1K
1L
1R
1a
0h
0/
0D
0Y
0n
0.
0C
1X
b0 $
b0 )
b100 #
b100 (
#325000
b101 !
b101 *
10
0B
11
0?
1/
b1 $
b1 )
#330000
00
b110 !
b110 *
1E
1B
0W
01
1F
1?
0T
0/
1D
b10 $
b10 )
#335000
b111 !
b111 *
10
0B
11
0?
1/
b11 $
b11 )
#340000
1o
0""
1+
0e
0Z
00
b1000 !
b1000 *
0E
1]
1l
1B
1W
0c
0[
01
0F
1_
1h
1?
1T
0`
0g
1i
0/
0D
1Y
b100 $
b100 )
#345000
b1001 !
b1001 *
10
0B
11
0?
1/
b101 $
b101 )
#350000
00
b1010 !
b1010 *
1E
1B
0W
01
1F
1?
0T
0/
1D
b110 $
b110 )
#355000
b1011 !
b1011 *
10
0B
11
0?
1/
b111 $
b111 )
#360000
0+
1e
1Z
1o
00
b1100 !
b1100 *
0E
0]
0l
0"
1""
1B
1W
1c
1[
1{
1!"
0#"
01
0F
0_
0h
0q
1p
1?
1T
1`
1g
1w
0~
0/
0D
0Y
1n
b1000 $
b1000 )
#365000
b1101 !
b1101 *
10
0B
11
0?
1/
b1001 $
b1001 )
#370000
00
b1110 !
b1110 *
1E
1B
0W
01
1F
1?
0T
0/
1D
b1010 $
b1010 )
#375000
b1111 !
b1111 *
10
0B
11
0?
1/
b1011 $
b1011 )
#380000
1"
0{
0o
1q
1#"
0w
0!"
1""
1+
0e
0Z
00
b0 !
b0 *
0E
1]
1l
1B
1W
0c
0[
01
0F
1_
1h
1?
1T
0`
0g
1i
0/
0D
1Y
b1100 $
b1100 )
#385000
b1 !
b1 *
10
0B
11
0?
1/
b1101 $
b1101 )
#390000
00
b10 !
b10 *
1E
1B
0W
01
1F
1?
0T
0/
1D
b1110 $
b1110 )
#395000
b11 !
b11 *
10
0B
11
0?
1/
b1111 $
b1111 )
#400000
0+
1e
1Z
0o
b101 !
b101 *
0E
0]
0l
0"
1""
1W
1c
1[
1{
1!"
0F
0_
0h
0q
0p
1?
1T
1`
1g
1w
1~
0>
0/
0D
0Y
0n
1.
b0 $
b0 )
b101 #
b101 (
#405000
1E
0V
1-
0;
b110 !
b110 *
00
13
1B
09
01
15
1>
06
0=
1?
1/
b1 $
b1 )
#410000
0o
1""
0+
1e
0]
1d
1Z
0-
0^
0l
1;
10
1a
1j
1k
b111 !
b111 *
1E
03
0B
0,
1V
19
11
1Q
1U
0W
05
0>
0G
1F
16
1=
1M
0T
0/
1D
b10 $
b10 )
#415000
1o
0""
1+
0e
1]
0d
0Z
1^
1l
0a
0j
1k
1,
0Q
0E
1G
1W
0M
0U
1V
1-
0;
b1000 !
b1000 *
00
13
1B
09
01
15
1>
06
0=
1?
1/
b11 $
b11 )
#420000
1d
0-
0^
1;
10
1a
b1001 !
b1001 *
0E
03
0B
0,
1V
1j
19
11
1Q
1U
0c
1f
0[
05
0>
0G
0F
1_
0\
1h
16
1=
1M
1T
0`
1b
0g
1i
0/
0D
1Y
b100 $
b100 )
#425000
1E
0V
1-
0;
b1010 !
b1010 *
00
13
1B
09
01
15
1>
06
0=
1?
1/
b101 $
b101 )
#430000
1d
1f
0-
0^
0\
0Z
1;
10
1a
1b
1k
b1011 !
b1011 *
1E
03
0B
0,
1V
19
11
1Q
1U
0W
05
0>
0G
1F
16
1=
1M
0T
0/
1D
b110 $
b110 )
#435000
0d
0f
1^
1\
1Z
0a
0b
0k
1,
0Q
0E
1G
1W
0M
0U
1V
1-
0;
b1100 !
b1100 *
00
13
1B
09
01
15
1>
06
0=
1?
1/
b111 $
b111 )
#440000
0+
1e
0]
1d
0-
0^
1Z
1;
10
1a
0E
1k
b1101 !
b1101 *
1o
03
0B
0,
1V
1j
0l
0"
1""
19
11
1Q
1U
1c
1f
1[
1{
1!"
0#"
05
0>
0G
0F
0_
0\
0h
0q
1p
16
1=
1M
1T
1`
1b
1g
1w
0~
0/
0D
0Y
1n
b1000 $
b1000 )
#445000
1E
0V
1-
0;
b1110 !
b1110 *
00
13
1B
09
01
15
1>
06
0=
1?
1/
b1001 $
b1001 )
#450000
0"
1{
1o
0q
0#"
1w
1!"
1""
0+
1e
0]
1d
1Z
0-
0^
0l
1;
10
1a
1j
1k
b1111 !
b1111 *
1E
03
0B
0,
1V
19
11
1Q
1U
0W
05
0>
0G
1F
16
1=
1M
0T
0/
1D
b1010 $
b1010 )
#455000
1"
0{
0o
1q
1#"
0w
0!"
1""
1+
0e
1]
0d
0Z
1^
1l
0a
0j
1k
1,
0Q
0E
1G
1W
0M
0U
1V
1-
0;
b0 !
b0 *
00
13
1B
09
01
15
1>
06
0=
1?
1/
b1011 $
b1011 )
#460000
1d
0-
0^
1;
10
1a
b1 !
b1 *
0E
03
0B
0,
1V
1j
19
11
1Q
1U
0c
1f
0[
05
0>
0G
0F
1_
0\
1h
16
1=
1M
1T
0`
1b
0g
1i
0/
0D
1Y
b1100 $
b1100 )
#465000
1E
0V
1-
0;
b10 !
b10 *
00
13
1B
09
01
15
1>
06
0=
1?
1/
b1101 $
b1101 )
#470000
1d
1f
0-
0^
0\
0Z
1;
10
1a
1b
1k
b11 !
b11 *
1E
03
0B
0,
1V
19
11
1Q
1U
0W
05
0>
0G
1F
16
1=
1M
0T
0/
1D
b1110 $
b1110 )
#475000
0d
0f
1^
1\
1Z
0a
0b
0k
1,
0Q
0E
1G
1W
0M
0U
1V
1-
0;
b100 !
b100 *
00
13
1B
09
01
15
1>
06
0=
1?
1/
b1111 $
b1111 )
#480000
0+
1e
1E
0]
0W
1d
1U
0^
1Z
0-
1a
1k
b110 !
b110 *
0o
1;
1P
0,
1j
0l
0"
1""
03
0H
1Q
1c
1f
1[
1{
1!"
19
1O
0G
0_
0\
0h
0q
0p
05
0I
1M
1T
1`
1b
1g
1w
1~
16
1=
1L
0S
0/
0D
0Y
0n
0.
1C
b0 $
b0 )
b110 #
b110 (
#485000
b111 !
b111 *
10
0B
11
0?
1/
b1 $
b1 )
#490000
1o
0""
1+
0e
1]
0d
0Z
1^
1l
0a
0j
1k
1,
0P
0E
b1000 !
b1000 *
00
1H
1W
1B
0N
0F
01
1J
1S
1?
0K
0R
1T
0/
1D
b10 $
b10 )
#495000
b1001 !
b1001 *
10
0B
11
0?
1/
b11 $
b11 )
#500000
1d
0^
1a
0,
0Z
1P
1E
1k
b1010 !
b1010 *
00
0H
0W
1j
1B
1N
1F
0c
1f
0[
01
0J
0S
1_
0\
1h
1?
1K
1R
0`
1b
0g
1i
0/
0D
1Y
b100 $
b100 )
#505000
b1011 !
b1011 *
10
0B
11
0?
1/
b101 $
b101 )
#510000
0d
0f
1^
1\
1Z
0a
0b
0k
1,
0P
0E
b1100 !
b1100 *
00
1H
1W
1B
0N
0F
01
1J
1S
1?
0K
0R
1T
0/
1D
b110 $
b110 )
#515000
b1101 !
b1101 *
10
0B
11
0?
1/
b111 $
b111 )
#520000
0+
1e
0]
1d
0^
1a
0,
1Z
1P
1E
1k
1o
b1110 !
b1110 *
00
0H
0W
1j
0l
0"
1""
1B
1N
1F
1c
1f
1[
1{
1!"
0#"
01
0J
0S
0_
0\
0h
0q
1p
1?
1K
1R
1`
1b
1g
1w
0~
0/
0D
0Y
1n
b1000 $
b1000 )
#525000
b1111 !
b1111 *
10
0B
11
0?
1/
b1001 $
b1001 )
#530000
1"
0{
0o
1q
1#"
0w
0!"
1""
1+
0e
1]
0d
0Z
1^
1l
0a
0j
1k
1,
0P
0E
b0 !
b0 *
00
1H
1W
1B
0N
0F
01
1J
1S
1?
0K
0R
1T
0/
1D
b1010 $
b1010 )
#535000
b1 !
b1 *
10
0B
11
0?
1/
b1011 $
b1011 )
#540000
1d
0^
1a
0,
0Z
1P
1E
1k
b10 !
b10 *
00
0H
0W
1j
1B
1N
1F
0c
1f
0[
01
0J
0S
1_
0\
1h
1?
1K
1R
0`
1b
0g
1i
0/
0D
1Y
b1100 $
b1100 )
#545000
b11 !
b11 *
10
0B
11
0?
1/
b1101 $
b1101 )
