roger/Lab3/a4_Round_Robin_FIFO_Arbiter.v
`timescale 1ns/1ps

module Round_Robin_FIFO_Arbiter(clk, rst_n, wen, a, b, c, d, dout, valid);
    input clk;
    input rst_n;
    input [4-1:0] wen;
    input [8-1:0] a, b, c, d;
    output [8-1:0] dout;
    output valid;

    wire [8-1:0] out [4-1:0];
    wire [4-1:0] error;
    reg [2-1:0] cnt;
    reg [2-1:0] cnt_delay;
    reg rst_n_c;

    FIFO_8 queue_a (clk, rst_n, wen[0], cnt[1:0]==2'd0, a, out[0], error[0]);
    FIFO_8 queue_b (clk, rst_n, wen[1], cnt[1:0]==2'd1, b, out[1], error[1]);
    FIFO_8 queue_c (clk, rst_n, wen[2], cnt[1:0]==2'd2, c, out[2], error[2]);
    FIFO_8 queue_d (clk, rst_n, wen[3], cnt[1:0]==2'd3, d, out[3], error[3]);

    assign valid = (rst_n_c) ? !error[cnt_delay[1:0]] : 1'b0;
    assign dout = (valid) ? out[cnt_delay[1:0]] : 8'b0;

    always @(posedge clk) rst_n_c <= rst_n;
    always @(posedge clk) cnt_delay <= cnt;
    always @(posedge clk) begin
        if (!rst_n) cnt <= 2'b0;
        else cnt <= cnt + 2'b1;
    end
endmodule

module FIFO_8(clk, rst_n, wen, ren, din, dout, error);
    input clk;
    input rst_n;
    input wen, ren;
    input [8-1:0] din;
    output [8-1:0] dout;
    output error;

    reg [8-1:0] dout;
    reg error;

    reg [8-1:0] MEM [8-1:0];
    reg [3-1:0] R_ptr;
    reg [3-1:0] W_ptr;
    reg [4-1:0] cnt;

    always @(posedge clk) begin
        if (!rst_n) begin
            // MEM[0] <= 8'b0;      // can be omitted
            // MEM[1] <= 8'b0;
            // MEM[2] <= 8'b0;
            // MEM[3] <= 8'b0;
            // MEM[4] <= 8'b0;
            // MEM[5] <= 8'b0;
            // MEM[6] <= 8'b0;
            // MEM[7] <= 8'b0;
            R_ptr <= 3'b0;
            W_ptr <= 3'b0;
            cnt <= 3'b0;
            error <= 1'b0;
            dout <= 8'b0;
        end else if (wen) begin
            if (cnt == 4'd8) error <= 1'b1;
            else begin
                error <= ren;       // if wen && ren => error
                MEM[W_ptr] <= din;
                W_ptr <= W_ptr + 3'b1;
                cnt <= cnt + 1'b1;
            end
        end else if (ren) begin
            if (cnt == 4'b0) error <= 1'b1;
            else begin
                error <= 1'b0;
                dout <= MEM[R_ptr];
                R_ptr <= R_ptr + 3'b1;
                cnt <= cnt - 1'b1;
            end
        end else error <= 1'b0;
    end
endmodule

roger/Lab3/a4_Round_Robin_FIFO_Arbiter_t.v
`include "a4_Round_Robin_FIFO_Arbiter.v"
`timescale 1ns/1ps

module Round_Robin_FIFO_Arbiter_t ();
    reg clk = 0, rst_n = 0;
    reg [3:0] wen;
    reg [8-1:0] a, b, c, d;
    wire [8-1:0] dout;
    wire valid;

    Round_Robin_FIFO_Arbiter RR(clk, rst_n, wen, a, b, c, d, dout, valid);

    always #5 clk = !clk;
    initial begin
        #10 rst_n = !rst_n;
    end
    initial begin
        wen = 4'b1111;
        #20 wen = 4'b1000;
        #10 wen = 4'b0100;
        #10 wen = 4'b0000;
        #30 wen = 4'b0001;
        #10 wen = 4'b0000;
        #40 wen = 4'b1111;
        #10 wen = 4'b0000;
        #50 $finish;
    end
    initial begin
        #10
        a = 87;
        b = 56;
        c = 9;
        d = 13;
        #10
        d = 85;
        a = 0;
        b = 0;
        c = 0;
        #10
        c = 139;
        d = 0;
        #10
        c = 0;
        #30
        a = 51;
        #10
        a = 0;
        #40
        a = 1;
        b = 2;
        c = 3;
        d = 4;
        rst_n = !rst_n;
        #10
        a = 0;
        b = 0;
        c = 0;
        d = 0;
        rst_n = !rst_n;
    end
    initial begin
        $dumpfile("a4.vcd");
        $dumpvars(0, Round_Robin_FIFO_Arbiter_t);
    end
endmodule

roger/Lab3/a4.vcd
$date
	Sat Oct 12 17:17:46 2024
$end
$version
	Icarus Verilog
$end
$timescale
	1ps
$end
$scope module Round_Robin_FIFO_Arbiter_t $end
$var wire 1 ! valid $end
$var wire 8 " dout [7:0] $end
$var reg 8 # a [7:0] $end
$var reg 8 $ b [7:0] $end
$var reg 8 % c [7:0] $end
$var reg 1 & clk $end
$var reg 8 ' d [7:0] $end
$var reg 1 ( rst_n $end
$var reg 4 ) wen [3:0] $end
$scope module RR $end
$var wire 8 * a [7:0] $end
$var wire 8 + b [7:0] $end
$var wire 8 , c [7:0] $end
$var wire 1 & clk $end
$var wire 8 - d [7:0] $end
$var wire 1 ( rst_n $end
$var wire 4 . wen [3:0] $end
$var wire 1 ! valid $end
$var wire 4 / error [3:0] $end
$var wire 8 0 dout [7:0] $end
$var reg 2 1 cnt [1:0] $end
$var reg 2 2 cnt_delay [1:0] $end
$var reg 1 3 rst_n_c $end
$scope module queue_a $end
$var wire 1 & clk $end
$var wire 8 4 din [7:0] $end
$var wire 1 5 ren $end
$var wire 1 ( rst_n $end
$var wire 1 6 wen $end
$var reg 3 7 R_ptr [2:0] $end
$var reg 3 8 W_ptr [2:0] $end
$var reg 4 9 cnt [3:0] $end
$var reg 8 : dout [7:0] $end
$var reg 1 ; error $end
$upscope $end
$scope module queue_b $end
$var wire 1 & clk $end
$var wire 8 < din [7:0] $end
$var wire 1 = ren $end
$var wire 1 ( rst_n $end
$var wire 1 > wen $end
$var reg 3 ? R_ptr [2:0] $end
$var reg 3 @ W_ptr [2:0] $end
$var reg 4 A cnt [3:0] $end
$var reg 8 B dout [7:0] $end
$var reg 1 C error $end
$upscope $end
$scope module queue_c $end
$var wire 1 & clk $end
$var wire 8 D din [7:0] $end
$var wire 1 E ren $end
$var wire 1 ( rst_n $end
$var wire 1 F wen $end
$var reg 3 G R_ptr [2:0] $end
$var reg 3 H W_ptr [2:0] $end
$var reg 4 I cnt [3:0] $end
$var reg 8 J dout [7:0] $end
$var reg 1 K error $end
$upscope $end
$scope module queue_d $end
$var wire 1 & clk $end
$var wire 8 L din [7:0] $end
$var wire 1 M ren $end
$var wire 1 ( rst_n $end
$var wire 1 N wen $end
$var reg 3 O R_ptr [2:0] $end
$var reg 3 P W_ptr [2:0] $end
$var reg 4 Q cnt [3:0] $end
$var reg 8 R dout [7:0] $end
$var reg 1 S error $end
$upscope $end
$upscope $end
$upscope $end
$enddefinitions $end
$comment Show the parameter values. $end
$dumpall
$end
#0
$dumpvars
xS
bx R
bx Q
bx P
bx O
1N
xM
bx L
xK
bx J
bx I
bx H
bx G
1F
xE
bx D
xC
bx B
bx A
bx @
bx ?
1>
x=
bx <
x;
bx :
bx 9
bx 8
bx 7
16
x5
bx 4
x3
bx 2
bx 1
bx 0
bx /
b1111 .
bx -
bx ,
bx +
bx *
b1111 )
0(
bx '
0&
bx %
bx $
bx #
bx "
x!
$end
#5000
b0 "
b0 0
0!
b0 :
0;
b0 9
b0 8
b0 7
b0 B
0C
b0 A
b0 @
b0 ?
b0 J
0K
b0 I
b0 H
b0 G
b0 R
b0 /
0S
b0 Q
b0 P
b0 O
03
15
0=
0E
0M
b0 1
1&
#10000
0&
b1101 '
b1101 -
b1101 L
b1001 %
b1001 ,
b1001 D
b111000 $
b111000 +
b111000 <
b1010111 #
b1010111 *
b1010111 4
1(
#15000
05
1=
b1 1
b0 2
13
b1 Q
b1 P
b1 I
b1 H
b1 A
b1 @
b1 9
b1 8
b1 /
1;
1&
#20000
06
0>
0F
0&
b0 %
b0 ,
b0 D
b0 $
b0 +
b0 <
b0 #
b0 *
b0 4
b1010101 '
b1010101 -
b1010101 L
b1000 )
b1000 .
#25000
b111000 "
b111000 0
1!
b0 /
0;
b0 A
b1 ?
b111000 B
b10 Q
b10 P
b1 2
0=
1E
b10 1
1&
#30000
1F
0N
0&
b0 '
b0 -
b0 L
b10001011 %
b10001011 ,
b10001011 D
b100 )
b100 .
#35000
0!
b0 "
b0 0
0E
1M
b11 1
b10 2
b10 I
b10 H
b100 /
1K
1&
#40000
0F
0&
b0 %
b0 ,
b0 D
b0 )
b0 .
#45000
b1101 "
b1101 0
1!
b0 /
0K
b1 Q
b1 O
b1101 R
b11 2
15
0M
b0 1
1&
#50000
0&
#55000
b1010111 "
b1010111 0
05
1=
b1 1
b0 2
b0 9
b1 7
b1010111 :
1&
#60000
0&
#65000
0!
b0 "
b0 0
b10 /
1C
b1 2
0=
1E
b10 1
1&
#70000
16
0&
b110011 #
b110011 *
b110011 4
b1 )
b1 .
#75000
b1001 "
b1001 0
1!
0E
1M
b11 1
b10 2
b1 I
b1 G
b1001 J
b0 /
0C
b1 9
b10 8
1&
#80000
06
0&
b0 #
b0 *
b0 4
b0 )
b0 .
#85000
b1010101 "
b1010101 0
b0 Q
b10 O
b1010101 R
b11 2
15
0M
b0 1
1&
#90000
0&
#95000
b110011 "
b110011 0
05
1=
b1 1
b0 2
b0 9
b10 7
b110011 :
1&
#100000
0&
#105000
0!
b0 "
b0 0
b10 /
1C
b1 2
0=
1E
b10 1
1&
#110000
0&
#115000
b10001011 "
b10001011 0
1!
0E
1M
b11 1
b10 2
b0 I
b10 G
b10001011 J
b0 /
0C
1&
#120000
16
1>
1F
1N
0&
0(
b100 '
b100 -
b100 L
b11 %
b11 ,
b11 D
b10 $
b10 +
b10 <
b1 #
b1 *
b1 4
b1111 )
b1111 .
#125000
0!
b0 "
b0 0
b0 :
b0 8
b0 7
b0 B
b0 @
b0 ?
b0 J
b0 H
b0 G
b0 R
b0 P
b0 O
03
b11 2
15
0M
b0 1
1&
#130000
06
0>
0F
0N
0&
1(
b0 '
b0 -
b0 L
b0 %
b0 ,
b0 D
b0 $
b0 +
b0 <
b0 #
b0 *
b0 4
b0 )
b0 .
#135000
05
1=
b1 1
b0 2
13
b1 /
1;
1&
#140000
0&
#145000
0;
b10 /
1C
b1 2
0=
1E
b10 1
1&
#150000
0&
#155000
0E
1M
b11 1
b10 2
1K
b100 /
0C
1&
#160000
0&
#165000
0K
b1000 /
1S
b11 2
15
0M
b0 1
1&
#170000
0&
#175000
05
1=
b1 1
b0 2
0S
b1 /
1;
1&
