roger/Lab4/a1_Content_Addressable_Memory.v
`timescale 1ns/1ps

module Content_Addressable_Memory(clk, wen, ren, din, addr, dout, hit);
    input clk;
    input wen, ren;
    input [8-1:0] din;
    input [4-1:0] addr;
    output reg [4-1:0] dout;
    output reg hit;

    reg [8-1:0] CAM [16-1:0];
    wire [16-1:0] match;

    assign match[0] = (CAM[0] === din);
    assign match[1] = (CAM[1] === din);
    assign match[2] = (CAM[2] === din);
    assign match[3] = (CAM[3] === din);
    assign match[4] = (CAM[4] === din);
    assign match[5] = (CAM[5] === din);
    assign match[6] = (CAM[6] === din);
    assign match[7] = (CAM[7] === din);
    assign match[8] = (CAM[8] === din);
    assign match[9] = (CAM[9] === din);
    assign match[10] = (CAM[10] === din);
    assign match[11] = (CAM[11] === din);
    assign match[12] = (CAM[12] === din);
    assign match[13] = (CAM[13] === din);
    assign match[14] = (CAM[14] === din);
    assign match[15] = (CAM[15] === din);

    always @(posedge clk) begin
        if (ren) begin
            hit <= |match;
            casez(match)
                16'b1???????????????: dout <= 4'd15;
                16'b01??????????????: dout <= 4'd14;
                16'b001?????????????: dout <= 4'd13;
                16'b0001????????????: dout <= 4'd12;
                16'b00001???????????: dout <= 4'd11;
                16'b000001??????????: dout <= 4'd10;
                16'b0000001?????????: dout <= 4'd9;
                16'b00000001????????: dout <= 4'd8;
                16'b000000001???????: dout <= 4'd7;
                16'b0000000001??????: dout <= 4'd6;
                16'b00000000001?????: dout <= 4'd5;
                16'b000000000001????: dout <= 4'd4;
                16'b0000000000001???: dout <= 4'd3;
                16'b00000000000001??: dout <= 4'd2;
                16'b000000000000001?: dout <= 4'd1;
                16'b0000000000000001: dout <= 4'd0;
                default: dout <= 4'd0;
            endcase
        end else if (wen) begin
            CAM[addr] <= din;
            hit <= 1'b0;
            dout <= 4'b0;
        end else begin
            hit <= 1'b0;
            dout <= 4'b0;
        end
    end
endmodule

roger/Lab4/a1_Content_Addressable_Memory_t.v
`include "a1_Content_Addressable_Memory.v"
`timescale 1ns/1ps

module Content_Addressable_Memory_t();
    reg clk = 1'd0;
    reg wen = 1'd0, ren = 1'd0;
    reg [7:0] din = 8'd0;
    reg [3:0] addr = 4'd0;
    wire [3:0] dout;
    wire hit;
    Content_Addressable_Memory CAM(clk, wen, ren, din, addr, dout, hit);
    
    always #5 clk = ~clk;
    
    initial begin
        #10 wen = 1;
        #40 wen = 0;
        #110 $finish;
    end

    initial begin
        #80 ren = 1;
        #50 ren = 0;
    end

    initial begin
        #10 addr = 4'd0;
        #10 addr = 4'd7;
        #10 addr = 4'd15;
        #10 addr = 4'd9;
        #10 addr = 4'd0;
    end

    initial begin
        #10 din = 8'd4;
        #10 din = 8'd8;
        #10 din = 8'd35;
        #10 din = 8'd8;
        #10 din = 8'd0;
        #30 din = 8'd4;
        #10 din = 8'd8;
        #10 din = 8'd35;
        #10 din = 8'd87;
        #10 din = 8'd45;
        #10 din = 8'd0;
    end

    initial begin
        $dumpfile("a1.vcd");
        $dumpvars(0, Content_Addressable_Memory_t);
    end
endmodule

roger/Lab4/a1.vcd
$date
	Sat Oct 19 17:05:39 2024
$end
$version
	Icarus Verilog
$end
$timescale
	1ps
$end
$scope module Content_Addressable_Memory_t $end
$var wire 1 ! hit $end
$var wire 4 " dout [3:0] $end
$var reg 4 # addr [3:0] $end
$var reg 1 $ clk $end
$var reg 8 % din [7:0] $end
$var reg 1 & ren $end
$var reg 1 ' wen $end
$scope module CAM $end
$var wire 4 ( addr [3:0] $end
$var wire 1 $ clk $end
$var wire 8 ) din [7:0] $end
$var wire 1 & ren $end
$var wire 1 ' wen $end
$var wire 16 * match [15:0] $end
$var reg 4 + dout [3:0] $end
$var reg 1 ! hit $end
$upscope $end
$upscope $end
$enddefinitions $end
$comment Show the parameter values. $end
$dumpall
$end
#0
$dumpvars
bx +
b0 *
b0 )
b0 (
0'
0&
b0 %
0$
b0 #
bx "
x!
$end
#5000
b0 "
b0 +
0!
1$
#10000
0$
b100 %
b100 )
1'
#15000
b1 *
1$
#20000
0$
b0 *
b1000 %
b1000 )
b111 #
b111 (
#25000
b10000000 *
1$
#30000
0$
b0 *
b100011 %
b100011 )
b1111 #
b1111 (
#35000
b1000000000000000 *
1$
#40000
0$
b10000000 *
b1000 %
b1000 )
b1001 #
b1001 (
#45000
b1010000000 *
1$
#50000
0$
b0 *
b0 %
b0 )
b0 #
b0 (
0'
#55000
1$
#60000
0$
#65000
1$
#70000
0$
#75000
1$
#80000
0$
b1 *
b100 %
b100 )
1&
#85000
1!
1$
#90000
0$
b1010000000 *
b1000 %
b1000 )
#95000
b1001 "
b1001 +
1$
#100000
0$
b1000000000000000 *
b100011 %
b100011 )
#105000
b1111 "
b1111 +
1$
#110000
0$
b0 *
b1010111 %
b1010111 )
#115000
b0 "
b0 +
0!
1$
#120000
0$
b101101 %
b101101 )
#125000
1$
#130000
0$
b0 %
b0 )
0&
