johnny/Lab5/Lab5_Team1_Booth_Multiplier_4bit.v
`timescale 1ns/1ps 

module Booth_Multiplier_4bit(clk, rst_n, start, a, b, p);
    input clk;
    input rst_n; 
    input start;
    input signed [3:0] a, b;
    output reg signed [7:0] p;
    wire signed [7:0] out;
    
    parameter WAIT = 3'b001;
    parameter CAL = 3'b010;
    parameter FINISH = 3'b100;
    reg [2:0] cnt_CAL;
    reg [2:0] cnt_FIN;
    reg [2:0] state, next_state = WAIT;

    booth_MUL BM(clk, state == CAL, a, b, out);

    always @(posedge clk) begin
        if(!rst_n) state <= WAIT;
        else state <= next_state;
    end

    always @(posedge clk) begin
        if(state == CAL) cnt_CAL <= cnt_CAL + 1;
        else cnt_CAL <= 0;
    end

    always @(posedge clk) begin
        if(state == FINISH) cnt_FIN <= cnt_FIN + 1;
        else cnt_FIN <= 0;
    end

    always @(*) begin
        case(state)
            WAIT:
                if(!start) next_state = WAIT;
                else next_state = CAL;
            CAL:
                if(cnt_CAL == 3) next_state = FINISH;
                else next_state = CAL;
            FINISH:
                if(cnt_FIN == 1) next_state = WAIT;
                else next_state = FINISH;
        endcase
    end

    always @(*) begin
        if(state == FINISH) begin
            if(!cnt_FIN) p = out;
            else p = p;
        end else begin
            p = 0;
        end
    end
endmodule

module booth_MUL(clk, rst_n, a, b, p);
    input clk, rst_n;
    input signed [3:0] a, b;
    output signed [7:0] p;
    reg [2:0] cnt;
    reg signed [9:0] P, A, S;
    wire signed [9:0] ADD, SUB;

    assign p = {P[8:1]};
    assign ADD = P + A;
    assign SUB = P + S;

    always @(posedge clk) begin
        if(!rst_n) begin
            A <= {a[3], a, 5'd0};
            if(a == 4'b1000) S <= {5'b01000, 5'd0};
            else if(a == 4'd0) S <= {10'd0};
            else S <= {/*n_A*/~a[3], -a, 5'd0};
            P <= {5'd0, b, 1'b0};
            cnt <= 3'd4;
        end else begin
            case ({P[1], P[0]})
                2'b01: begin
                    A <= A;
                    S <= S;
                    P <= {ADD[9], ADD[9:1]};
                    cnt <= cnt - 1;
                end
                2'b10: begin
                    A <= A;
                    S <= S;
                    P <= {SUB[9], SUB[9:1]};
                    cnt <= cnt - 1;
                end
                default: begin
                    A <= A;
                    S <= S;
                    P <= {P[9], P[9:1]};
                    cnt <= cnt - 1;
                end
            endcase
        end
    end
endmodule

johnny/Lab5/Lab5_Team1_Booth_Multiplier_4bit_t.v
`timescale 1ns/1ps

module Booth_Multiplier_4bit_t();
    reg clk = 0, rst_n = 0, start = 0;
    reg signed [3:0] a = 4'b1000, b = 4'b1000;
    wire signed [7:0] p;
    
    Booth_Multiplier_4bit BM4(clk, rst_n, start, a, b, p);

    always #5 clk = ~clk;

    initial begin
        #10 rst_n = 1;
    end

    initial begin
        #10
        a = 4'd7;
        b = 4'd0;
        #50
        $display("a = ", $signed(a), ", b = ", $signed(b), ", p = ", $signed(p), "\n");
        #20
        a = 4'd0;
        b = 4'd7;
        #50
        $display("a = ", $signed(a), ", b = ", $signed(b), ", p = ", $signed(p), "\n");
        #20
        a = 4'd0;
        b = 4'd7;
        #50
        $display("a = ", $signed(a), ", b = ", $signed(b), ", p = ", $signed(p), "\n");
        #20
        a = 4'd7;
        b = 4'd7;
        #50
        $display("a = ", $signed(a), ", b = ", $signed(b), ", p = ", $signed(p), "\n");
        #20
        a = 4'b1000;
        b = 4'd0;
        #50
        $display("a = ", $signed(a), ", b = ", $signed(b), ", p = ", $signed(p), "\n");
        #20
        a = 4'd0;
        b = 4'b1000;
        #50
        $display("a = ", $signed(a), ", b = ", $signed(b), ", p = ", $signed(p), "\n");
        #20
        a = 4'd5;
        b = 4'b1000;
        #50
        $display("a = ", $signed(a), ", b = ", $signed(b), ", p = ", $signed(p), "\n");
        #20
        a = 4'd4;
        b = 4'b1000;
        #50
        $display("a = ", $signed(a), ", b = ", $signed(b), ", p = ", $signed(p), "\n");
        #20
        a = 4'b1011;
        b = 4'd7;
        #50
        $display("a = ", $signed(a), ", b = ", $signed(b), ", p = ", $signed(p), "\n");
        #20
        a = 4'b1100;
        b = 4'b1100;
        #50
        $display("a = ", $signed(a), ", b = ", $signed(b), ", p = ", $signed(p), "\n");
        #20
        a = 4'b1101;
        b = 4'd0;
        #50
        $display("a = ", $signed(a), ", b = ", $signed(b), ", p = ", $signed(p), "\n");
        #20
        a = 4'b1001;
        b = 4'd7;
        #50
        $display("a = ", $signed(a), ", b = ", $signed(b), ", p = ", $signed(p), "\n");
        #20
        a = 4'd7;
        b = 4'd5;
        #50
        $display("a = ", $signed(a), ", b = ", $signed(b), ", p = ", $signed(p), "\n");
        #20
        #10 $finish;
    end
        
    initial begin
        #10 start = 1;
        #10 start = 0;
        #60 start = 1;
        #10 start = 0;
        #60 start = 1;
        #10 start = 0;
        #60 start = 1;
        #10 start = 0;
        #60 start = 1;
        #10 start = 0;
        #60 start = 1;
        #10 start = 0;
        #60 start = 1;
        #10 start = 0;
        #60 start = 1;
        #10 start = 0;
        #60 start = 1;
        #10 start = 0;
        #60 start = 1;
        #10 start = 0;
        #60 start = 1;
        #10 start = 0;
        #60 start = 1;
        #10 start = 0;
        #60 start = 1;
        #10 start = 0;
    end
endmodule

johnny/Lab5/Booth_Multiplier_4bit_t.vcd
$date
	Thu Nov 07 23:12:21 2024
$end
$version
	Icarus Verilog
$end
$timescale
	1ps
$end
$scope module Booth_Multiplier_4bit_t $end
$var wire 8 ! p [7:0] $end
$var reg 4 " a [3:0] $end
$var reg 4 # b [3:0] $end
$var reg 1 $ clk $end
$var reg 1 % rst_n $end
$var reg 1 & start $end
$scope module BM4 $end
$var wire 4 ' a [3:0] $end
$var wire 4 ( b [3:0] $end
$var wire 1 $ clk $end
$var wire 1 % rst_n $end
$var wire 1 & start $end
$var wire 8 ) out [7:0] $end
$var reg 3 * cnt_CAL [2:0] $end
$var reg 3 + cnt_FIN [2:0] $end
$var reg 3 , next_state [2:0] $end
$var reg 8 - p [7:0] $end
$var reg 3 . state [2:0] $end
$scope module BM $end
$var wire 4 / a [3:0] $end
$var wire 4 0 b [3:0] $end
$var wire 1 $ clk $end
$var wire 1 1 rst_n $end
$var wire 8 2 p [7:0] $end
$var wire 10 3 SUB [9:0] $end
$var wire 10 4 ADD [9:0] $end
$var reg 10 5 A [9:0] $end
$var reg 10 6 P [9:0] $end
$var reg 10 7 S [9:0] $end
$var reg 3 8 cnt [2:0] $end
$upscope $end
$upscope $end
$upscope $end
$enddefinitions $end
#0
$dumpvars
bx 8
bx 7
bx 6
bx 5
bx 4
bx 3
bx 2
x1
b1000 0
b1000 /
bx .
bx -
b1 ,
bx +
bx *
bx )
b1000 (
b1000 '
0&
0%
0$
b1000 #
b1000 "
bx !
$end
#5000
b0 !
b0 -
01
b1 .
b0 *
b0 +
1$
#10000
b10 ,
0$
1&
b0 #
b0 (
b0 0
b111 "
b111 '
b111 /
1%
#15000
b0 )
b0 2
11
b10 .
b100 8
b11100000 4
b1100100000 3
b0 6
b1100100000 7
b11100000 5
1$
#20000
0$
0&
#25000
b11 8
b1 *
1$
#30000
0$
#35000
b10 *
b10 8
1$
#40000
0$
#45000
b100 ,
b1 8
b11 *
1$
#50000
0$
#55000
b100 *
01
b100 .
b0 8
1$
#60000
0$
#65000
b1 ,
b100 8
b0 *
b1 +
1$
#70000
0$
#75000
b10 +
b1 .
1$
#80000
b10 ,
0$
b111 #
b111 (
b111 0
b0 "
b0 '
b0 /
1&
#85000
b111 )
b111 2
b1110 6
b1110 3
b0 7
b1110 4
b0 5
11
b10 .
b0 +
1$
#90000
0$
0&
#95000
b11 )
b11 2
b1 *
b11 8
b111 4
b111 3
b111 6
1$
#100000
0$
#105000
b1 )
b1 2
b10 8
b11 4
b11 3
b11 6
b10 *
1$
#110000
0$
#115000
b100 ,
b0 )
b0 2
b11 *
b1 8
b1 4
b1 3
b1 6
1$
#120000
0$
#125000
b0 8
b0 4
b0 3
b0 6
01
b100 .
b100 *
1$
#130000
0$
#135000
b1 ,
b111 )
b111 2
b1 +
b0 *
b100 8
b1110 4
b1110 3
b1110 6
1$
#140000
0$
#145000
b1 .
b10 +
1$
#150000
b10 ,
0$
1&
#155000
b0 +
11
b10 .
1$
#160000
0$
0&
#165000
b11 )
b11 2
b11 8
b111 4
b111 3
b111 6
b1 *
1$
#170000
0$
#175000
b1 )
b1 2
b10 *
b10 8
b11 4
b11 3
b11 6
1$
#180000
0$
#185000
b0 )
b0 2
b100 ,
b1 8
b1 4
b1 3
b1 6
b11 *
1$
#190000
0$
#195000
b100 *
01
b100 .
b0 8
b0 4
b0 3
b0 6
1$
#200000
0$
#205000
b111 )
b111 2
b1 ,
b100 8
b1110 4
b1110 3
b1110 6
b0 *
b1 +
1$
#210000
0$
#215000
b10 +
b1 .
1$
#220000
b10 ,
0$
b111 "
b111 '
b111 /
1&
#225000
b1100101110 3
b1100100000 7
b11101110 4
b11100000 5
11
b10 .
b0 +
1$
#230000
0$
0&
#235000
b11001011 )
b11001011 2
b1 *
b11 8
b1110111 4
b1010110111 3
b1110010111 6
1$
#240000
0$
#245000
b11100101 )
b11100101 2
b10 8
b10101011 4
b1011101011 3
b1111001011 6
b10 *
1$
#250000
0$
#255000
b100 ,
b11110010 )
b11110010 2
b11 *
b1 8
b11000101 4
b1100000101 3
b1111100101 6
1$
#260000
0$
#265000
b110001 )
b110001 2
b110001 !
b110001 -
b0 8
b101000010 4
b1110000010 3
b1100010 6
01
b100 .
b100 *
1$
#270000
0$
#275000
b1 ,
b111 )
b111 2
b1 +
b0 *
b100 8
b11101110 4
b1100101110 3
b1110 6
1$
#280000
0$
#285000
b0 !
b0 -
b1 .
b10 +
1$
#290000
b10 ,
0$
b0 #
b0 (
b0 0
b1000 "
b1000 '
b1000 /
1&
#295000
b0 )
b0 2
b0 +
11
b10 .
b0 6
b100000000 3
b100000000 7
b1100000000 4
b1100000000 5
1$
#300000
0$
0&
#305000
b11 8
b1 *
1$
#310000
0$
#315000
b10 *
b10 8
1$
#320000
0$
#325000
b100 ,
b1 8
b11 *
1$
#330000
0$
#335000
b100 *
01
b100 .
b0 8
1$
#340000
0$
#345000
b1 ,
b100 8
b0 *
b1 +
1$
#350000
0$
#355000
b10 +
b1 .
1$
#360000
b10 ,
0$
b1000 #
b1000 (
b1000 0
b0 "
b0 '
b0 /
1&
#365000
b1000 )
b1000 2
b10000 6
b10000 3
b0 7
b10000 4
b0 5
11
b10 .
b0 +
1$
#370000
0$
0&
#375000
b100 )
b100 2
b1 *
b11 8
b1000 4
b1000 3
b1000 6
1$
#380000
0$
#385000
b10 )
b10 2
b10 8
b100 4
b100 3
b100 6
b10 *
1$
#390000
0$
#395000
b100 ,
b1 )
b1 2
b11 *
b1 8
b10 4
b10 3
b10 6
1$
#400000
0$
#405000
b0 )
b0 2
b0 !
b0 -
b0 8
b1 4
b1 3
b1 6
01
b100 .
b100 *
1$
#410000
0$
#415000
b1 ,
b1000 )
b1000 2
b1 +
b0 *
b100 8
b10000 4
b10000 3
b10000 6
1$
#420000
0$
#425000
b1 .
b10 +
1$
#430000
b10 ,
0$
b101 "
b101 '
b101 /
1&
#435000
b0 +
11
b10 .
b1101110000 3
b1101100000 7
b10110000 4
b10100000 5
1$
#440000
0$
0&
#445000
b100 )
b100 2
b11 8
b10101000 4
b1101101000 3
b1000 6
b1 *
1$
#450000
0$
#455000
b10 )
b10 2
b10 *
b10 8
b10100100 4
b1101100100 3
b100 6
1$
#460000
0$
#465000
b1 )
b1 2
b100 ,
b1 8
b10100010 4
b1101100010 3
b10 6
b11 *
1$
#470000
0$
#475000
b11011000 !
b11011000 -
b11011000 )
b11011000 2
b100 *
01
b100 .
b0 8
b1010001 4
b1100010001 3
b1110110001 6
1$
#480000
0$
#485000
b1000 )
b1000 2
b1 ,
b100 8
b10110000 4
b1101110000 3
b10000 6
b0 *
b1 +
1$
#490000
0$
#495000
b0 !
b0 -
b10 +
b1 .
1$
#500000
b10 ,
0$
b100 "
b100 '
b100 /
1&
#505000
b1110010000 3
b1110000000 7
b10010000 4
b10000000 5
11
b10 .
b0 +
1$
#510000
0$
0&
#515000
b100 )
b100 2
b1 *
b11 8
b10001000 4
b1110001000 3
b1000 6
1$
#520000
0$
#525000
b10 )
b10 2
b10 8
b10000100 4
b1110000100 3
b100 6
b10 *
1$
#530000
0$
#535000
b100 ,
b1 )
b1 2
b11 *
b1 8
b10000010 4
b1110000010 3
b10 6
1$
#540000
0$
#545000
b11100000 )
b11100000 2
b11100000 !
b11100000 -
b0 8
b1000001 4
b1101000001 3
b1111000001 6
01
b100 .
b100 *
1$
#550000
0$
#555000
b1 ,
b1000 )
b1000 2
b1 +
b0 *
b100 8
b10010000 4
b1110010000 3
b10000 6
1$
#560000
0$
#565000
b0 !
b0 -
b1 .
b10 +
1$
#570000
b10 ,
0$
b111 #
b111 (
b111 0
b1011 "
b1011 '
b1011 /
1&
#575000
b111 )
b111 2
b0 +
11
b10 .
b1110 6
b10101110 3
b10100000 7
b1101101110 4
b1101100000 5
1$
#580000
0$
0&
#585000
b101011 )
b101011 2
b11 8
b1110110111 4
b11110111 3
b1010111 6
b1 *
1$
#590000
0$
#595000
b10101 )
b10101 2
b10 *
b10 8
b1110001011 4
b11001011 3
b101011 6
1$
#600000
0$
#605000
b1010 )
b1010 2
b100 ,
b1 8
b1101110101 4
b10110101 3
b10101 6
b11 *
1$
#610000
0$
#615000
b11011101 !
b11011101 -
b11011101 )
b11011101 2
b100 *
01
b100 .
b0 8
b1100011010 4
b1011010 3
b1110111010 6
1$
#620000
0$
#625000
b111 )
b111 2
b1 ,
b100 8
b1101101110 4
b10101110 3
b1110 6
b0 *
b1 +
1$
#630000
0$
#635000
b0 !
b0 -
b10 +
b1 .
1$
#640000
b10 ,
0$
b1100 #
b1100 (
b1100 0
b1100 "
b1100 '
b1100 /
1&
#645000
b1100 )
b1100 2
b11000 6
b10011000 3
b10000000 7
b1110011000 4
b1110000000 5
11
b10 .
b0 +
1$
#650000
0$
0&
#655000
b110 )
b110 2
b1 *
b11 8
b1110001100 4
b10001100 3
b1100 6
1$
#660000
0$
#665000
b11 )
b11 2
b10 8
b1110000110 4
b10000110 3
b110 6
b10 *
1$
#670000
0$
#675000
b100 ,
b100001 )
b100001 2
b11 *
b1 8
b1111000011 4
b11000011 3
b1000011 6
1$
#680000
0$
#685000
b10000 )
b10000 2
b10000 !
b10000 -
b0 8
b1110100001 4
b10100001 3
b100001 6
01
b100 .
b100 *
1$
#690000
0$
#695000
b1 ,
b1100 )
b1100 2
b1 +
b0 *
b100 8
b1110011000 4
b10011000 3
b11000 6
1$
#700000
0$
#705000
b0 !
b0 -
b1 .
b10 +
1$
#710000
b10 ,
0$
b0 #
b0 (
b0 0
b1101 "
b1101 '
b1101 /
1&
#715000
b0 )
b0 2
b0 +
11
b10 .
b0 6
b1100000 3
b1100000 7
b1110100000 4
b1110100000 5
1$
#720000
0$
0&
#725000
b11 8
b1 *
1$
#730000
0$
#735000
b10 *
b10 8
1$
#740000
0$
#745000
b100 ,
b1 8
b11 *
1$
#750000
0$
#755000
b100 *
01
b100 .
b0 8
1$
#760000
0$
#765000
b1 ,
b100 8
b0 *
b1 +
1$
#770000
0$
#775000
b10 +
b1 .
1$
#780000
b10 ,
0$
b111 #
b111 (
b111 0
b1001 "
b1001 '
b1001 /
1&
#785000
b111 )
b111 2
b1110 6
b11101110 3
b11100000 7
b1100101110 4
b1100100000 5
11
b10 .
b0 +
1$
#790000
0$
0&
#795000
b111011 )
b111011 2
b1 *
b11 8
b1110010111 4
b101010111 3
b1110111 6
1$
#800000
0$
#805000
b11101 )
b11101 2
b10 8
b1101011011 4
b100011011 3
b111011 6
b10 *
1$
#810000
0$
#815000
b100 ,
b1110 )
b1110 2
b11 *
b1 8
b1100111101 4
b11111101 3
b11101 6
1$
#820000
0$
#825000
b11001111 )
b11001111 2
b11001111 !
b11001111 -
b0 8
b1010111110 4
b1111110 3
b1110011110 6
01
b100 .
b100 *
1$
#830000
0$
#835000
b1 ,
b111 )
b111 2
b1 +
b0 *
b100 8
b1100101110 4
b11101110 3
b1110 6
1$
#840000
0$
#845000
b0 !
b0 -
b1 .
b10 +
1$
#850000
b10 ,
0$
b101 #
b101 (
b101 0
b111 "
b111 '
b111 /
1&
#855000
b101 )
b101 2
b0 +
11
b10 .
b1010 6
b1100101010 3
b1100100000 7
b11101010 4
b11100000 5
1$
#860000
0$
0&
#865000
b11001010 )
b11001010 2
b11 8
b1110101 4
b1010110101 3
b1110010101 6
b1 *
1$
#870000
0$
#875000
b11101 )
b11101 2
b10 *
b10 8
b100011010 4
b1101011010 3
b111010 6
1$
#880000
0$
#885000
b11010110 )
b11010110 2
b100 ,
b1 8
b10001101 4
b1011001101 3
b1110101101 6
b11 *
1$
#890000
0$
#895000
b100011 !
b100011 -
b100011 )
b100011 2
b100 *
01
b100 .
b0 8
b100100110 4
b1101100110 3
b1000110 6
1$
#900000
0$
#905000
b101 )
b101 2
b1 ,
b100 8
b11101010 4
b1100101010 3
b1010 6
b0 *
b1 +
1$
#910000
0$
#915000
b0 !
b0 -
b10 +
b1 .
1$
#920000
0$
#925000
b0 +
1$
