johnny/Lab5/Lab5_Team1_Sliding_Window_Sequence_Detector.v
`timescale 1ns/1ps

module Sliding_Window_Sequence_Detector (clk, rst_n, in, dec);
    input clk, rst_n;
    input in;
    output dec;
    reg dec;

    parameter S0 = 8'b00000000;
    parameter S1 = 8'b00000001;
    parameter S2 = 8'b00000011;
    parameter S3 = 8'b00000111;
    parameter S4 = 8'b00001110;
    parameter S5 = 8'b00011100;
    parameter S6 = 8'b00111001;

    parameter S7 = 8'b01110010;
    parameter S8 = 8'b01110011;

    reg [7:0] state, next_state = S0;

    always @(posedge clk) begin
        if (!rst_n) state <= S0;
        else state <= next_state;
    end

    always @(*) begin
        case (state)
            S0:
                if (in) next_state = S1;
                else next_state = S0;
            S1:
                if (in) next_state = S2;
                else next_state = S1;
            S2:
                if (in) next_state = S3;
                else next_state = S0;
            S3:
                if (in) next_state = S3;
                else next_state = S4;
            S4:
                if (in) next_state = S1;
                else next_state = S5;
            S5:
                if (in) next_state = S6;
                else next_state = S0;
            S6:
                if (in) next_state = S8;
                else next_state = S7;
            S7:
                if (in) next_state = S6;
                else next_state = S0;
            default:
                if (in) next_state = S3;
                else next_state = S0;
        endcase
    end

    always @(*) begin
        case(state)
            S8: 
                if(in) dec <= 1;
                else dec <= 0;
            default: 
                dec <= 0;
        endcase
    end
endmodule

johnny/Lab5/Lab5_Team1_Sliding_Window_Sequence_Detector_t.v
`include "Lab5_Team1_Sliding_Window_Sequence_Detector.v"
`timescale 1ns / 1ps

module Sliding_Window_Sequence_Detector_t ();
    reg clk = 0, rst_n = 0, in = 0;
    wire dec;
    Sliding_Window_Sequence_Detector SWSD(clk, rst_n, in, dec);

    always #5 clk = ~clk;

    initial begin
        #10 rst_n = 1;
    end

    initial begin
        #10 in = 1;
        #30 in = 0;
        #20 in = 1;
        #40 in = 0;
        #20 in = 1;
        #10 in = 0;
        #10 in = 1;
        #30 in = 0;
        #30 in = 1;
        #30 in = 0;
        #10 in = 1;
        #30 in = 0;
        #20 in = 1;
        #10 in = 0;
        #50 $finish;
    end

    initial begin
        $dumpfile("Sliding_Window_Sequence_Detector_t.vcd");
        $dumpvars(0, Sliding_Window_Sequence_Detector_t);
    end
endmodule

johnny/Lab5/Sliding_Window_Sequence_Detector_t.vcd
$date
	Thu Oct 31 22:41:03 2024
$end
$version
	Icarus Verilog
$end
$timescale
	1ps
$end
$scope module Sliding_Window_Sequence_Detector_t $end
$var wire 1 ! dec $end
$var reg 1 " clk $end
$var reg 1 # in $end
$var reg 1 $ rst_n $end
$scope module SWSD $end
$var wire 1 " clk $end
$var wire 1 # in $end
$var wire 1 $ rst_n $end
$var reg 1 ! dec $end
$var reg 8 % next_state [7:0] $end
$var reg 8 & state [7:0] $end
$upscope $end
$upscope $end
$enddefinitions $end
#0
$dumpvars
bx &
b0 %
0$
0#
0"
0!
$end
#5000
b0 &
1"
#10000
b1 %
0"
1#
1$
#15000
b11 %
b1 &
1"
#20000
0"
#25000
b111 %
b11 &
1"
#30000
0"
#35000
b111 &
1"
#40000
b1110 %
0"
0#
#45000
b11100 %
b1110 &
1"
#50000
0"
#55000
b0 %
b11100 &
1"
#60000
b111001 %
0"
1#
#65000
b1110011 %
b111001 &
1"
#70000
0"
#75000
1!
b111 %
b1110011 &
1"
#80000
0"
#85000
0!
b111 &
1"
#90000
0"
#95000
1"
#100000
b1110 %
0"
0#
#105000
b11100 %
b1110 &
1"
#110000
0"
#115000
b0 %
b11100 &
1"
#120000
b111001 %
0"
1#
#125000
b1110011 %
b111001 &
1"
#130000
b1110010 %
0"
0#
#135000
b0 %
b1110010 &
1"
#140000
b111001 %
0"
1#
#145000
b1110011 %
b111001 &
1"
#150000
0"
#155000
1!
b111 %
b1110011 &
1"
#160000
0"
#165000
0!
b111 &
1"
#170000
b1110 %
0"
0#
#175000
b11100 %
b1110 &
1"
#180000
0"
#185000
b0 %
b11100 &
1"
#190000
0"
#195000
b0 &
1"
#200000
b1 %
0"
1#
#205000
b11 %
b1 &
1"
#210000
0"
#215000
b111 %
b11 &
1"
#220000
0"
#225000
b111 &
1"
#230000
b1110 %
0"
0#
#235000
b11100 %
b1110 &
1"
#240000
b1 %
0"
1#
#245000
b11 %
b1 &
1"
#250000
0"
#255000
b111 %
b11 &
1"
#260000
0"
#265000
b111 &
1"
#270000
b1110 %
0"
0#
#275000
b11100 %
b1110 &
1"
#280000
0"
#285000
b0 %
b11100 &
1"
#290000
b111001 %
0"
1#
#295000
b1110011 %
b111001 &
1"
#300000
b1110010 %
0"
0#
#305000
b0 %
b1110010 &
1"
#310000
0"
#315000
b0 &
1"
